Workbook

Sheet 1. BRIEFING
A2: CLIENTE: | B2: - | F2: SUA LOGO AQUI!
A3: ARQ.: | B3: -
A4: OBRA: | B4: -
A5: PLANILHA DE BRIEFING COM CLIENTE E AUTOR DO PROJETO
A6: ITEM | B6: DESCRIÇÃO | C6: UND | D6: QNTD | E6: MEM CAL | F6: OBSERVAÇÕES
A8: 1 | B8: SERVIÇOS ADIMINSTRATIVOS
A9: 1.1 | B9: ADMINISTRAÇÃO DE OBRA | C9: MES | D9: =E9 -> 1 | E9: 1
A10: 1.2 | B10: TRANSPORTE E ALIMENTAÇÃO EQP ADM | C10: MES | D10: =E10 -> 1 | E10: 1
A11: 1.3 | B11: ART DE EXECUÇÃO DA OBRA | C11: UN | D11: =E11 -> 1 | E11: 1
A12: 1.4 | B12: ISOLAMENTO/PROTEÇÃO COM LONA/PLÁSTICO BOLHA | C12: VB | D12: =E12 -> 1 | E12: 1
A13: 1.5 | B13: MOBILIZAÇÃO E DESMOBILIZAÇÃO | C13: UN | D13: =E13 -> 1 | E13: 1
A14: 2 | B14: DEMOLIÇÃO E RETIRADA
A15: 2.1 | B15: DEMOLIÇÃO DE ALVENARIA DE VEDAÇÃO | C15: M² | D15: =E15 -> 1,00 | E15: 1,00
A16: 2.2 | B16: REMOÇÃO DE BANCADAS EM GRANITO | C16: UND | D16: =E16 -> 1,00 | E16: 1,00
A17: 2.3 | B17: REMOÇÃO DE LOUÇAS E METAIS | C17: VB | D17: =E17 -> 1,00 | E17: 1,00
A18: 2.4 | B18: REMOÇÃO DE PORTAS INTERNAS EM MADEIRA | C18: UN | D18: =E18 -> 1,00 | E18: 1,00
A19: 2.5 | B19: DEMOLIÇÃO DE REVESTIMENTO CERÂMICO EM PAREDE | C19: M² | D19: =E19 -> 1,00 | E19: 1,00
A20: 2.6 | B20: DEMOLIÇÃO DE REVESTIMENTO CERÂMICO EM PISO | C20: M² | D20: =E20 -> 1,00 | E20: 1,00
A21: 2.7 | B21: DEMOLIÇÃO DE FORRO EM GESSO/PVC | C21: M² | D21: =E21 -> 1,00 | E21: 1,00
A22: 2.8 | B22: REMOÇÃO DE LUMINÁRIAS INTERNAS (FORRO) | C22: UN | D22: =E22 -> 1,00 | E22: 1,00
A23: 2.9 | B23: REMOÇÃO DOS ENTULHOS POR SACOS E CARRO PEQUENO | C23: UN | D23: =E23 -> 1,00 | E23: 1,00
A24: 3 | B24: SERVIÇO EM ALVENARIA
A25: 3.1 | B25: ASSENTAMENTO DE ALVENARIA DE VEDAÇÃO | C25: M² | D25: =E25 -> 1 | E25: 1
A26: 3.2 | D26: =E26 -> 0
A27: 3.3 | D27: =E27 -> 0
A28: 3.4 | D28: =E28 -> 0
A29: 4 | B29: INSTALAÇÃO HIDRÁULICA
A30: 4.1 | B30: INSTALAÇAO DE PONTO DE ÁGUA FRIA | C30: UN | D30: =E30 -> 10 | E30: 10
A31: 4.2 | B31: INSTALAÇÃO DE PONTO DE ESGOTO 50 MM | C31: UN | D31: =E31 -> 1 | E31: 1
A32: 4.3 | B32: RELOCAÇÃO DE PONTO DE ESGOTO 100 MM | C32: UN | D32: =E32 -> 1 | E32: 1
A33: 4.4 | B33: INSTALAÇÃO DE PONTO DE REGISTRO DE GAVETA | C33: UN | D33: =E33 -> 1 | E33: 1
A34: 4.5 | B34: INSTALAÇÃO DE PONTO DE REGISTRO DE PRESSÃO | C34: UN | D34: =E34 -> 1 | E34: 1
A35: 5 | B35: INSTALAÇÃO ELÉTRICA
A36: 5.1 | B36: INSTALAÇÃO DE INFRAESTRUTURA PARA TOMADA E ILUMINAÇÃO | C36: UN | D36: =E36 -> 1 | E36: 1
A37: 5.2 | B37: INSTALAÇÃO DE CABEAMENTO PARA PONTOS DE TOMADAS | C37: UN | D37: =E37 -> 1 | E37: 1
A38: 5.3 | B38: INSTALAÇÃO DE CABEAMENTO PARA PONTOS DE ILUMINAÇÃO | C38: UN | D38: =E38 -> 1 | E38: 1
A39: 5.4 | B39: REISNTALAÇÃO DE QUADRO DE DISTRIBUIÇÃO (ADEQUAÇÃO) | C39: VB | D39: =E39 -> 1 | E39: 1
A40: 5.5 | B40: INSTALAÇÃO DE INFRAESTRUTURA PARA PONTOS DE REDE/ANTENA/CAMERA/SOM | C40: UN | D40: =E40 -> 1 | E40: 1
A41: 6 | B41: INSTALAÇÃO DE EQUIPAMENTOS
A42: 6.1 | B42: INSTALAÇÃO DE INFRA PARA AR CONDICIONADO | C42: UN | D42: =E42 -> 1 | E42: 1
A43: 6.2 | B43: INSTALAÇÃO DE BOILER | C43: UN | D43: =E43 -> 1 | E43: 1
A44: 6.3 | B44: INSTALAÇÃO DE EXAUSTOR l BWC CAMARIM E MAS | C44: UN | D44: =E44 -> 1 | E44: 1
A45: 7 | B45: INSTALAÇÃO DE ILUMINAÇÃO
A46: 7.1 | B46: INSTALAÇÃO DE LUMINÁRIA DE EMBUTIR QUADRADA 20W EM FORRO DE GESSO | C46: UN | D46: =E46 -> 1 | E46: 1
A47: 7.2 | B47: INSTALAÇÃO DE DICROICAS DIRECIONAIS | C47: UN | D47: =E47 -> 1 | E47: 1
A48: 7.3 | B48: INSTALAÇÃO DE FITA EM LED | C48: UN | D48: =E48 -> 1 | E48: 1
A49: 7.4 | B49: INSTALAÇÃO DE PENDENTE | C49: UN | D49: =E49 -> 1 | E49: 1
A50: 7.5 | B50: INSTALAÇÃO DE INTERRUPTOR SIMPLES | C50: UN | D50: =E50 -> 1 | E50: 1 | F50: CONSID. PIAL ZEFFIA
A51: 7.6 | C51: UN | D51: =E51 -> 1 | E51: 1
A52: 7.7 | C52: UN | D52: =E52 -> 1 | E52: 1
A53: 7.8 | C53: UN | D53: =E53 -> 1 | E53: 1
A54: 8 | B54: SERVIÇO EM FORRO
A55: 8.1 | B55: FORNECIMENTO E INSTALAÇÃO DE FORRO EM GESSO | C55: M² | D55: =E55 -> 1 | E55: 1
A56: 8.2 | B56: FORNECIMENTO E INSTALAÇÃO DE JUNTA EM DILATAÇÃO 3X3 CM | C56: M | D56: =E56 -> 1 | E56: 1
A57: 8.3 | B57: FORNECIMENTO E INSTALAÇÃO DE CORTINEIRO | C57: M | D57: =E57 -> 1 | E57: 1
A58: 8.4 | B58: FORNECIMENTO E INSTALAÇÃO DE SANCAS | C58: M | D58: =E58 -> 1 | E58: 1
A59: 9 | B59: SERVIÇO EM ESQUADRIA DE MADEIRA
A60: 9.1 | B60: FORNECIMENTO E INSTALAÇÃO DE PORTA EM MADEIRA 0,60 x 2,10 m l COMPLETA | C60: UN | D60: =E60 -> 1 | E60: 1
A61: 9.2 | B61: FORNECIMENTO E INSTALAÇÃO DE PORTA EM MADEIRA 0,70 X 2,10 M l COMPLETA | C61: UN | D61: =E61 -> 1 | E61: 1
A62: 9.3 | B62: FORNECIMENTO E INSTALAÇÃO DE PORTA EM MADEIRA 0,80 X 2,10 M l COMPLETA | C62: UN | D62: =E62 -> 1 | E62: 1
A63: 9.4 | B63: FORNECIMENTO E INSTALAÇÃO DE PORTA EM MADEIRA 0,90 X 2,10 M l COMPLETA | C63: UN | D63: =E63 -> 1 | E63: 1
A64: 9.5 | B64: FORNECIMENTO E INSTALAÇÃO DE PORTA EM MADEIRA 0,90 X 2,10 M l COMPLETA | C64: UN | D64: =E64 -> 1 | E64: 1
A65: 9.6 | B65: FORNECIMENTO E INSTALAÇÃO DE PORTA EM MADEIRA 0,90 X 2,10 M l COMPLETA | C65: UN | D65: =E65 -> 1 | E65: 1
A66: 10 | B66: SERVIÇO DE MARMORARIA
A67: 10.1 | B67: FORNECIMENTO E INSTALAÇÃO DE BANCADA EM GRANITO | C67: VB | D67: =E67 -> 1 | E67: 1
A68: 10.2 | B68: FORNECIMENTO E INSTALAÇÃO DE NICHO EM GRANITO | C68: VB | D68: =E68 -> 1 | E68: 1
A69: 10.3 | B69: FORNECIMENTO E INSTALAÇÃO DE DIVBOX EM GRANITO | C69: VB | D69: =E69 -> 1 | E69: 1
A70: 10.4 | B70: FORNECIMENTO E INSTALAÇÃO DE NICHO EM GRANITO | C70: VB | D70: =E70 -> 1 | E70: 1
A71: 11 | B71: REVESTIMENTO EM ARGAMASSA
A72: 11.1 | B72: APLICAÇÃO DE CHAPISCO E REBOCO EM PAREDE DE ALVENARIA NOVA | C72: M² | D72: =E72 -> 1 | E72: 1
A73: 11.2 | B73: REGULARIZAÇÃO COM REBOCO FINO PARA RECEBIMENTO DE REVESTIMENTO NOVO | C73: M² | D73: =E73 -> 1 | E73: 1
A74: 11.3 | B74: REGULARIZAÇÃO DE PISO COM ATÉ 5 CM PARA RECEBIMENTO DE REVESTIMENTO NONO | C74: M² | D74: =E74 -> 1 | E74: 1
A75: 12 | B75: REVESTIMENTO EM PORCELANATO
A76: 12.1 | B76: REVESTIMENTO EM PISO ÁREA COMUM l BIANCOGRÉS CRISTALLO 60X60 CM | C76: M² | D76: =E76 -> 1 | E76: 1
A77: 12.2 | B77: REVESTIMENTO EM PISO ÁREA MOLHADA l BIANCOGRÉS CRISTALLO 60X60 CM | C77: M² | D77: =E77 -> 1 | E77: 1
A78: 12.3 | B78: REVESTIMENTO EM PAREDE COZINHA l POINTER 60X60 CM | C78: M² | D78: =E78 -> 1 | E78: 1
A79: 12.4 | B79: REVESTIMENTO EM PAREDE BANHEIROS l POINTER 60X60 CM | C79: M² | D79: =E79 -> 1 | E79: 1
A80: 12.5 | B80: REVESTIMENTO EM PAREDE ÁREA DE SERVIÇO l POINTER 60X60 CM | C80: M² | D80: =E80 -> 1 | E80: 1
A81: 12.6 | B81: REVESTIMENTO EM PAREDE VARANDA l POINTER 60X60 CM | C81: M² | D81: =E81 -> 1 | E81: 1
A82: 13 | B82: LOUÇAS E METAIS
A83: 13.1 | B83: INSTALAÇÃO DE VASO SANITÁRIO COM CX ACOPLADA l ECOLUS CELITE BRANCA | C83: UN | D83: =E83 -> 1 | E83: 1
A84: 13.2 | B84: INSTALAÇÃO DE CUBA SUSPENSA DE CANTO EM LOUÇA BRANCA l CELITE | C84: UN | D84: =E84 -> 1 | E84: 1
A85: 13.3 | B85: INSTALAÇÃO DE TORNEIRA BICA ALTA | C85: UN | D85: =E85 -> 1 | E85: 1
A86: 13.4 | B86: INSTALAÇÃO DE PORTA ACESSÓRIOS l KIT BANHEIRO | C86: UN | D86: =E86 -> 1 | E86: 1
A87: 13.5 | B87: INSTALAÇÃO DE DUCHA HIGIÊNCIA | C87: UN | D87: =E87 -> 1 | E87: 1
A88: 13.6 | B88: INSTALAÇÃO DE CHUVEIRO | C88: UN | D88: =E88 -> 1 | E88: 1
A89: 14 | B89: SERVIÇO EM PINTURA
A90: 14.1 | B90: APLICAÇÃO DE SELADOR ACRILICO PAREDE E FORRO | C90: M2 | D90: =E90 -> 1 | E90: 1
A91: 14.2 | B91: APLICAÇÃO E LIXAMENTO DE MASSA CORRIDA EM FORRO DE GESSO | C91: M2 | D91: =E91 -> 1 | E91: 1
A92: 14.3 | B92: APLICAÇÃO DE TINTA EM FORRO EM GESSO COM TINA ACRÍLLICA ACETINADO NA COR | C92: M² | D92: =E92 -> 1 | E92: 1
A93: 14.4 | B93: APLICAÇÃO E LIXAMENTO DE MASSA CORRIDA EM PAREDE | C93: M² | D93: =E93 -> 1 | E93: 1
A94: 14.5 | B94: APLICAÇÃO DE TINTA ACRÍLICA EM PAREDE , ACETINADO COR | C94: M² | D94: =E94 -> 1 | E94: 1
A95: 14.6 | B95: APLICAÇÃO DE FUNDO, MASSA E TINTA EM PORTA DE MADEIRA, ACETINADO NA COR | C95: UND | D95: =E95 -> 1 | E95: 1
A96: 15 | B96: LIMPEZA FINAL
A97: 15.1 | B97: LIMPEZA FINAL DA OBRA | C97: VB | D97: =E97 -> 1 | E97: 1
A98: 15.3 | B98: REMOÇÃO DE ENTULHOS GERADOS PELA OBRA POR CARRO PEQUENOS | C98: UN | D98: =E98 -> 1 | E98: 1

Sheet 2. LEV QNT
B1: LEVANTAMENTO DE QUANTITATIVOS EM PAREDES
C2: MEDIDAS | F2: ALVENARIA | I2: PINTURA | L2: REVESTIMENTO (M²)
B3: AMBIENTE | C3: PERIMETRO | D3: PÉ DIREITO | E3: DESCONTOS | F3: ALVENARIA (M²) | G3: CHAPISCO (M²) | H3: REBOCO (M²) | I3: SELADOR (M²) | J3: MASSA CORRIDA (M²) | K3: PINTURA (M²) | L3: PORCELANTO | M3: CERÂMICA
B4: SALA | F4: =(C4*D4)-E4 -> 0 | G4: =F4 -> 0 | H4: =G4 -> 0
B5: QRT 01 | F5: =(C5*D5)-E5 -> 0 | G5: =F5 -> 0 | H5: =G5 -> 0
B6: QRT 02 | F6: =(C6*D6)-E6 -> 0 | G6: =F6 -> 0 | H6: =G6 -> 0
B7: QRT 03 | F7: =(C7*D7)-E7 -> 0 | G7: =F7 -> 0 | H7: =G7 -> 0
B8: CORREDOR | F8: =(C8*D8)-E8 -> 0 | G8: =F8 -> 0 | H8: =G8 -> 0
B9: QRT DEPENDENCIA | F9: =(C9*D9)-E9 -> 0 | G9: =F9 -> 0 | H9: =G9 -> 0
B10: BWC SOCIAL | F10: =(C10*D10)-E10 -> 0 | G10: =F10 -> 0 | H10: =G10 -> 0
B11: BWC SUITE 1 | F11: =(C11*D11)-E11 -> 0 | G11: =F11 -> 0 | H11: =G11 -> 0
B12: BWC SUITE 2 | F12: =(C12*D12)-E12 -> 0 | G12: =F12 -> 0 | H12: =G12 -> 0
B13: BWC SUITE 3 | F13: =(C13*D13)-E13 -> 0 | G13: =F13 -> 0 | H13: =G13 -> 0
F14: =(C14*D14)-E14 -> 0 | G14: =F14 -> 0 | H14: =G14 -> 0
F15: =(C15*D15)-E15 -> 0 | G15: =F15 -> 0 | H15: =G15 -> 0
F16: =(C16*D16)-E16 -> 0 | G16: =F16 -> 0 | H16: =G16 -> 0
F17: =(C17*D17)-E17 -> 0 | G17: =F17 -> 0 | H17: =G17 -> 0
F18: =(C18*D18)-E18 -> 0 | G18: =F18 -> 0 | H18: =G18 -> 0
F19: =(C19*D19)-E19 -> 0 | G19: =F19 -> 0 | H19: =G19 -> 0
F20: =(C20*D20)-E20 -> 0 | G20: =F20 -> 0 | H20: =G20 -> 0
F21: =(C21*D21)-E21 -> 0 | G21: =F21 -> 0 | H21: =G21 -> 0
F22: =(C22*D22)-E22 -> 0 | G22: =F22 -> 0 | H22: =G22 -> 0
F23: =(C23*D23)-E23 -> 0 | G23: =F23 -> 0 | H23: =G23 -> 0
F24: =(C24*D24)-E24 -> 0 | G24: =F24 -> 0 | H24: =G24 -> 0
B26: LEVANTAMENTO DE QUANTITATIVOS EM PISO E FORRO
D27: REVESTIMENTO | G27: PISO | I27: FORRO
B28: AMBIENTE | C28: ÁREA | D28: PORCELAN. | E28: CERÂMICA | F28: GRANITO | G28: CONTRAPISO | H28: IMPERMEAB | I28: GESSO | J28: SELADOR/MASSA | K28: PINTURA
B29: SALA | C29: 12.08 | D29: 0 | E29: 12.08 | F29: 0 | G29: 0 | H29: 0
B30: QRT 01 | C30: 7.8 | D30: 0 | E30: 7.8 | F30: 0 | G30: 0 | H30: 0
B31: QRT 02 | C31: 7.8 | D31: 0 | E31: 7.8 | F31: 0 | G31: 0 | H31: 0
B32: QRT 03 | C32: 0 | D32: 0 | E32: 0 | F32: 0 | G32: 0 | H32: 0
B33: CORREDOR | C33: 2.57 | D33: 0 | E33: 2.57 | F33: 0 | G33: 0 | H33: 0
B34: QRT DEPENDENCIA | C34: 0 | D34: 0 | E34: 0 | F34: 0 | G34: 0 | H34: 0
B35: BWC SOCIAL | C35: 0 | D35: 0 | E35: 0 | F35: 0 | G35: 0 | H35: 0
B36: BWC SUITE 1 | C36: 0 | D36: 0 | E36: 0 | F36: 0 | G36: 0 | H36: 0
B37: BWC SUITE 2 | C37: 0 | D37: 0 | E37: 0 | F37: 0 | G37: 0 | H37: 0
B38: BWC SUITE 3 | C38: 0 | D38: 0 | E38: 0 | F38: 0 | G38: 0 | H38: 0
B39: COZINHA/A. SERV | C39: 6.84 | D39: 0 | E39: 6.84 | F39: 0 | G39: 0 | H39: 0
D40: 0 | F40: 0 | G40: 0 | H40: 0
B41: TOTAL | C41: =SUM(C29:C39) -> 37.09 | D41: 0 | F41: 0 | G41: 0 | H41: 0
D42: 0 | F42: 0 | G42: 0 | H42: 0
D43: 0 | F43: 0 | G43: 0 | H43: 0
D44: 0 | F44: 0 | G44: 0 | H44: 0
D45: 0 | F45: 0 | G45: 0 | H45: 0
D46: 0 | F46: 0 | G46: 0 | H46: 0
D47: 0 | F47: 0 | G47: 0 | H47: 0
D48: 0 | F48: 0 | G48: 0 | H48: 0
F49: 0 | G49: 0 | H49: 0

Sheet 3. CPU
A1: CLIENTE: | B1: ='1. BRIEFING'!B2 -> - | G1: FUNÇÃO | H1: R$ HORA | I1: FUNÇÃO | J1: R$ HORA
A2: ARQ.: | B2: ='1. BRIEFING'!B3 -> - | E2: CUSTO MO | F2: 0 | G2: PEDREIRO | H2: 25.38 | I2: GESSEIRO | J2: 25.18
A3: OBRA: | B3: ='1. BRIEFING'!B4 -> - | E3: CUSTO MAT | F3: 0 | G3: SERVENTE | H3: 20.42 | I3: ELETRICISTA | J3: 25.69
B4: ='1. BRIEFING'!B5 -> 0 | E4: CUSTO SERV | F4: 0 | G4: ENCANDOR | H4: 24.63 | I4: AZULEJISTA | J4: 25.25
E5: CUSTO TOTAL | F5: 0 | G5: AUX. ENCANADOR | H5: 19.82
A6: COMPOSIÇÃO DE PREÇO UNITÁRIO PROPRIA
A7: ITEM | B7: DESCRIÇÃO DOS SERVIÇOS | C7: UND | D7: QNTD | E7: R$ UNIT | F7: R$ TOTAL | G7: COEFIC. | H7: R$ HORA
A8: ='1. BRIEFING'!A14 -> 2 | B8: ='1. BRIEFING'!B14 -> DEMOLIÇÃO E RETIRADA
A9: ='1. BRIEFING'!A15 -> 2.1 | B9: ='1. BRIEFING'!B15 -> DEMOLIÇÃO DE ALVENARIA DE VEDAÇÃO | C9: M2 | D9: ='1. BRIEFING'!D15 -> 1,00 | E9: =F9/D9 -> 62.5 | F9: =SUM(F10:F12) -> 62.5 | G9: COEF. | H9: R$ HORA
A10: MAT | B10: SACOS PARA ENTULHO | C10: UN | D10: 1 | E10: 2.5 | F10: =(E10*D10)*$D$9 -> 2.5
A11: MO | B11: PEDREIRO l DEMOLIÇÃO DE ALVENARIA | C11: M2 | D11: 1 | E11: 30 | F11: =(E11*D11)*$D$9 -> 30 | G11: 0.255 | H11: =H2 -> 25.38
A12: MO | B12: SERVENTE l DEMOLIÇÃO DE ALVENARIA | C12: M2 | D12: 1 | E12: 30 | F12: =(E12*D12)*$D$9 -> 30 | G12: 2.325 | H12: =H3 -> 20.42
C13: MO | D13: =F12/D9 -> 30 | E13: MAT | F13: =F10/D9 -> 2.5
A14: ='1. BRIEFING'!A16 -> 2.2 | B14: ='1. BRIEFING'!B16 -> REMOÇÃO DE BANCADAS EM GRANITO | C14: UN | D14: ='1. BRIEFING'!D16 -> 1,00 | E14: =F14/D14 -> 50 | F14: =SUM(F15) -> 50 | G14: COEF. | H14: R$ HORA
A15: MO | B15: SERVENTE l REMOÇÃO DE BANCADA EM GRANITO | C15: UN | D15: 1 | E15: 50 | F15: =(E15*D15)*D14 -> 50 | G15: 0.2 | H15: =H3 -> 20.42
C16: MO | D16: =F15/D14 -> 50 | E16: MAT | F16: 0
A17: ='1. BRIEFING'!A17 -> 2.3 | B17: ='1. BRIEFING'!B17 -> REMOÇÃO DE LOUÇAS E METAIS | C17: UN | D17: ='1. BRIEFING'!D17 -> 1,00 | E17: =F17/D17 -> 1027 | F17: =SUM(F18:F20) -> 1027 | G17: COEF. | H17: R$ HORA
A18: MO | B18: ENCANADOR l REMOÇÃO DE LOUÇAS E METAIS | C18: UN | D18: 1 | E18: 20 | F18: =(E18*D18)*D16 -> 1000 | G18: 0.1755 | H18: =H4 -> 24.63
A19: MO | B19: SERVENTE l REMOÇÃO DE LOUÇAS E METAIS | C19: UN | D19: 1 | E19: 25 | F19: =(E19*D19)*D17 -> 25 | G19: 0.3448 | H19: =H3 -> 20.42
A20: MAT | B20: SACOS PARA ENTULHO | C20: UN | D20: 1 | E20: 2 | F20: =(E20*D20)*D17 -> 2
C21: MO | D21: =SUM(F18:F19)/D17 -> 1025 | E21: MAT | F21: =F20/D17 -> 2
A22: ='1. BRIEFING'!A18 -> 2.4 | B22: ='1. BRIEFING'!B18 -> REMOÇÃO DE PORTAS INTERNAS EM MADEIRA | C22: UN | D22: ='1. BRIEFING'!D18 -> 1,00 | E22: =F22/D22 -> 70 | F22: =SUM(F23:F24) -> 70 | G22: COEF. | H22: R$ HORA
A23: MO | B23: PEDREIRO l REMOÇÃO DE PORTA EM MADEIRA | C23: UN | D23: 1 | E23: 50 | F23: =(E23*D23)*D22 -> 50 | G23: 0.1315 | H23: =H2 -> 25.38
A24: MO | B24: SERVENTE l REMOÇÃO DE PORTA EM MADEIRA | C24: UN | D24: 1 | E24: 20 | F24: =(E24*D24)*D22 -> 20 | G24: 0.2582 | H24: =H3 -> 20.42
C25: MO | D25: =F24/D22 -> 20 | E25: MAT | F25: 0
A26: ='1. BRIEFING'!A19 -> 2.5 | B26: ='1. BRIEFING'!B19 -> DEMOLIÇÃO DE REVESTIMENTO CERÂMICO EM PAREDE | C26: M2 | D26: ='1. BRIEFING'!D19 -> 1,00 | E26: =F26/D26 -> 12.5 | F26: =SUM(F28:F29) -> 12.5 | G26: COEF. | H26: R$ HORA
A27: MO | B27: AZULEJISTA l DEMOLIÇÃO DE REVESTIMENTO CERÂMICO EM PAREDE | C27: M² | D27: 1 | E27: 20 | F27: =(E27*D27)*$D$26 -> 20 | G27: 0.2553 | H27: =J4 -> 25.25
A28: MO | B28: SERVENTE l DEMOLIÇÃO DE REVESTIMENTO CERÂMICO EM PAREDE | C28: M² | D28: 1 | E28: 10 | F28: =(E28*D28)*$D$26 -> 10 | G28: 0.7195 | H28: =H3 -> 20.42
A29: MAT | B29: SACOS PARA ENTULHO | C29: UN | D29: 1 | E29: 2.5 | F29: =(E29*D29)*$D$26 -> 2.5
C30: MO | D30: =F28/D26 -> 10 | E30: MAT | F30: =(F28+F29)/D26 -> 12.5
A31: ='1. BRIEFING'!A20 -> 2.6 | B31: ='1. BRIEFING'!B20 -> DEMOLIÇÃO DE REVESTIMENTO CERÂMICO EM PISO | C31: M2 | D31: ='1. BRIEFING'!D20 -> 1,00 | E31: =F31/D31 -> 27.5 | F31: =SUM(F33:F34) -> 27.5 | G31: COEF. | H31: R$ HORA
A32: MO | B32: AZULEJISTA l DEMOLIÇÃO DE REVESTIMENTO CERÂMICO EM PISO | C32: M² | D32: 1 | E32: 20 | F32: =(E32*D32)*$D$26 -> 20 | G32: 0.2553 | H32: =J4 -> 25.25
A33: MO | B33: SERVENTE l DEMOLIÇÃO DE REVESTIMENTO CERÂMICO EM PISO | C33: M² | D33: 1 | E33: 25 | F33: =(E33*D33)*$D$31 -> 25 | G33: 0.7195 | H33: =H3 -> 20.42
A34: MAT | B34: SACOS PARA ENTULHO | C34: UN | D34: 1 | E34: 2.5 | F34: =(E34*D34)*$D$31 -> 2.5
C35: MO | D35: =F33/D31 -> 25 | E35: MAT | F35: =F34/D31 -> 2.5
A36: ='1. BRIEFING'!A21 -> 2.7 | B36: ='1. BRIEFING'!B21 -> DEMOLIÇÃO DE FORRO EM GESSO/PVC | C36: M2 | D36: ='1. BRIEFING'!D21 -> 1,00 | E36: =F36/D36 -> 9.5 | F36: =SUM(F38:F39) -> 9.5 | G36: COEF. | H36: R$ HORA
A37: MO | B37: GESSEIRO l DEMOLIÇÃO DE FORRO EM GESSO/PVC | C37: M² | D37: 1 | E37: 5 | F37: =(E37*D37)*$D$36 -> 5 | G37: 0.0713 | H37: =J2 -> 25.18
A38: MO | B38: SERVENTE l DEMOLIÇÃO DE FORRO EM GESSO/PVC | C38: M² | D38: 1 | E38: 7 | F38: =(E38*D38)*$D$36 -> 7 | G38: 0.1401 | H38: =H3 -> 20.42
A39: MAT | B39: SACO PARA ENTULHO | C39: UN | D39: 1 | E39: 2.5 | F39: =(E39*D39)*$D$36 -> 2.5
C40: MO | D40: =F38/D36 -> 7 | E40: MAT | F40: =F39/D36 -> 2.5
A41: ='1. BRIEFING'!A22 -> 2.8 | B41: ='1. BRIEFING'!B22 -> REMOÇÃO DE LUMINÁRIAS INTERNAS (FORRO) | C41: UN | D41: ='1. BRIEFING'!D22 -> 1,00 | E41: =F41/D41 -> 5 | F41: =SUM(F43:F44) -> 5 | G41: COEF. | H41: R$ HORA
A42: MO | B42: ELETRICISTA l REMOÇÃO DE LUMINÁRIAS EM GERAL | C42: UN | D42: 1 | E42: 5 | F42: =(E42*D42)*$D$41 -> 5 | G42: 0.0183 | H42: =J3 -> 25.69
A43: MO | B43: SERVENTE l REMOÇÃO DE LUMINÁRIAS EM GERAL | C43: UN | D43: 1 | E43: 2.5 | F43: =(E43*D43)*$D$41 -> 2.5 | G43: 0.0359 | H43: =H3 -> 20.42
A44: MAT | B44: SACOS PARA ENTULHO | C44: UN | D44: 1 | E44: 2.5 | F44: =(E44*D44)*$D$41 -> 2.5
C45: MO | D45: =F43/D41 -> 2.5 | E45: MAT | F45: =F44/D41 -> 2.5
A46: ='1. BRIEFING'!A23 -> 2.9 | B46: ='1. BRIEFING'!B23 -> REMOÇÃO DOS ENTULHOS POR SACOS E CARRO PEQUENO | C46: UN | D46: ='1. BRIEFING'!D23 -> 1,00 | E46: =F46/D46 -> 200 | F46: =SUM(F47:F48) -> 200 | G46: COEF. | H46: R$ HORA
A47: MO | B47: SERVENTE l REMOÇÃO DOS ENTULHOS ATÉ O LOCAL DE DESCARTE | C47: UN | D47: 1 | E47: 80 | F47: =(E47*D47)*$D$46 -> 80 | G47: 0.102 | H47: =H3 -> 20.42
A48: SERV | B48: REMOÇÃO DO ENTULHO EM CARRO PEQUENO | C48: UN | D48: 1 | E48: 120 | F48: =(E48*D48)*$D$46 -> 120
C49: MO | D49: =F47/D46 -> 80 | E49: SERV | F49: =F48/D46 -> 120
A50: ='1. BRIEFING'!A24 -> 3 | B50: ='1. BRIEFING'!B24 -> SERVIÇO EM ALVENARIA
A51: ='1. BRIEFING'!A25 -> 3.1 | B51: ='1. BRIEFING'!B25 -> ASSENTAMENTO DE ALVENARIA DE VEDAÇÃO | C51: M2 | D51: ='1. BRIEFING'!D25 -> 1 | E51: =F51/D51 -> 70.284256 | F51: =SUM(F52:F57) -> 70.284256 | G51: COEF. | H51: R$ HORA
A52: MO | B52: PEDREIRO l ASSENTAMENTO DE ALVENARIA | C52: M² | D52: 1 | E52: 30 | F52: =(E52*D52)*$D$51 -> 30 | G52: 1.61 | H52: =H2 -> 25.38
A53: MO | B53: SERVENTE l ASSENTAMENTO DE ALVENARIA | C53: M² | D53: 1 | E53: 0 | F53: =(E53*D53)*$D$51 -> 0 | G53: 0.805 | H53: =H3 -> 20.42
A54: MAT | B54: TIJOLO CERÂMICO 8 FUROS | C54: UND | D54: 28.31 | E54: 0.9 | F54: =(E54*D54)*$D$51 -> 25.479
A55: MAT | B55: ARGAMASSA TRAÇO 1:2:8 PARA ASSENTAMENTO DE ALVENARIA | C55: M³ | D55: 0.008 | E55: =F355 -> 1580.2858 | F55: =(E55*D55)*$D$51 -> 12.642286
A56: MAT | B56: TELA DE AÇO SOLDADA GALVANIZADA PARA ALVENARIA, FIO D= 1,20 A 1,70 MM, MALHA 15X15 MM | C56: M | D56: 0.6 | E56: 3 | F56: =(E56*D56)*$D$51 -> 1.8
A57: MAT | B57: PINO DE AÇO COM FURO, HASTE 27MM | C57: CENT | D57: 0.009 | E57: 40.33 | F57: =(E57*D57)*$D$51 -> 0.36297
C58: MO | D58: =SUM(F52:F53)/D51 -> 30 | E58: MAT | F58: =SUM(F54:F57)/D51 -> 40.284256
A59: ='1. BRIEFING'!A29 -> 4 | B59: ='1. BRIEFING'!B29 -> INSTALAÇÃO HIDRÁULICA
A60: ='1. BRIEFING'!A30 -> 4.1 | B60: ='1. BRIEFING'!B30 -> INSTALAÇAO DE PONTO DE ÁGUA FRIA | C60: UN | D60: ='1. BRIEFING'!D30 -> 10 | E60: =F60/D60 -> 70.72316 | F60: =SUM(F61:F68) -> 707.2316
A61: MO | B61: ENCANADOR l INSTALAÇÃO DE PTO DE ÁGUA FRIA | C61: UN | D61: 1 | E61: 50 | F61: =(E61*D61)*$D$60 -> 500 | G61: =0.38+0.15+0.15+0.2+0.07+0.05 -> 1 | H61: =H4 -> 24.63
A62: MO | B62: AUXILIAR ENCANADOR l INSTALAÇÃO DE PTO DE ÁGUA FRIA | C62: UN | D62: 1 | E62: 0 | F62: =(E62*D62)*$D$60 -> 0 | G62: =0.38+0.15+0.15+0.2+0.45+0.4 -> 1.73 | H62: =H5 -> 19.82
A63: MAT | B63: ADESIVO PLASTICO PARA PVC, FRASCO COM *850* GR | C63: UN | D63: 0.008 | E63: 3.52 | F63: =(E63*D63)*$D$60 -> 0.2816
A64: MAT | B64: TUBO PVC, SOLDAVEL, DE 25 MM, AGUA FRIA | C64: M | D64: 2 | E64: 4.5 | F64: =(E64*D64)*$D$60 -> 90
A65: MAT | B65: JOELHO PVC, SOLDAVEL, 90 GRAUS, 25 MM, COR MARROM, PARA AGUA FRIA PREDIAL | C65: UN | D65: 1 | E65: 0.77 | F65: =(E65*D65)*$D$60 -> 7.7
A66: MAT | B66: LIXA D'AGUA EM FOLHA, GRAO 100 | C66: UN | D66: 0.21 | E66: 2.5 | F66: =(E66*D66)*$D$60 -> 5.25
A67: MAT | B67: JOELHO PVC, SOLDAVEL, COM BUCHA DE LATAO, 90 GRAUS, 25 MM X 3/4", PARA AGUA FRIA | C67: UN | D67: 1 | E67: 8.9 | F67: =(E67*D67)*$D$60 -> 89
A68: MAT | B68: TE SOLDAVEL, PVC, 90 GRAUS, 25 MM, PARA AGUA FRIA PREDIAL | C68: UN | D68: 1 | E68: 1.5 | F68: =(E68*D68)*$D$60 -> 15
C69: MO | D69: =SUM(F61:F62)/D60 -> 50 | E69: MAT | F69: =SUM(F63:F68)/D60 -> 20.72316
A70: ='1. BRIEFING'!A31 -> 4.2 | B70: ='1. BRIEFING'!B31 -> INSTALAÇÃO DE PONTO DE ESGOTO 50 MM | C70: UN | D70: ='1. BRIEFING'!D31 -> 1 | E70: =F70/D70 -> 335.14478 | F70: =SUM(F71:F81) -> 335.14478
A71: MO | B71: ENCANADOR l INSTALAÇÃO DE PTO ESGOTO 50MM | C71: UN | D71: 1 | E71: 50 | F71: =(E71*D71)*$D$70 -> 50 | G71: =0.3182+0.14+0.14+0.09+1.2 -> 1.8882 | H71: =H4 -> 24.63
A72: MO | B72: AUX. ENCANADOR l INSTALAÇÃO DE PTO ESGOTO 50MM | C72: UN | D72: 1 | E72: 20 | F72: =(E72*D72)*$D$70 -> 20 | G72: =0.3182+0.14+0.14+0.09+0.187 -> 0.8752 | H72: =H5 -> 19.82
A73: MAT | B73: ADESIVO PLASTICO PARA PVC, FRASCO COM 850 GRCR | C73: UN | D73: 0.05 | E73: 23.81 | F73: =(E73*D73)*$D$70 -> 1.1905
A74: MAT | B74: JOELHO PVC SOLD 90G PB P/ ESG PREDIAL DN 50MM | C74: UN | D74: 1 | E74: 15.57 | F74: =(E74*D74)*$D$70 -> 15.57
A75: MAT | B75: JOLEHO PVC SOLD 45G PB P/ ESG PREDIAL DN 50MM | C75: UN | D75: 1 | E75: 2.3 | F75: =(E75*D75)*$D$70 -> 2.3
A76: MAT | B76: TUBO PVC SERIE NORMAL, DN 50 MM, PARA ESGOTO PREDIAL | C76: M | D76: 3 | E76: 8.85 | F76: =(E76*D76)*$D$70 -> 26.55
A77: MAT | B77: TE SANITARIO, PVC, DN 100 X 50 MM, SERIE NORMAL, PARA ESGOTO PREDIAL | C77: UN | D77: 1 | E77: 16.24 | F77: =(E77*D77)*$D$70 -> 16.24
A78: MAT | B78: LUVA SIMPLES, PVC, SOLD, DN 50MM, ESG PREDIAL | C78: UN | D78: 1 | E78: 2.93 | F78: =(E78*D78)*$D$70 -> 2.93
A79: MAT | B79: LIXA D'AGUA EM FOLHA, GRAO 100 | C79: UN | D79: 3 | E79: 2.3 | F79: =(E79*D79)*$D$60 -> 69
A80: MAT | B80: ANEL BORRACHA PARA TUBO ESGOTO, DN 50 MM | C80: UN | D80: 4 | E80: 2.3 | F80: =(E80*D80)*$D$60 -> 92
A81: MAT | B81: ARGAMASSA TRAÇO 1:3 PARA CHUMBAMENTO DE TUBOS | C81: M³ | D81: 0.006 | E81: =F361 -> 656.0714 | F81: =(E81*D81)*$D$60 -> 39.364284
C82: MO | D82: =SUM(F71:F72)/D70 -> 70 | E82: MAT | F82: =SUM(F73:F81)/D70 -> 265.14478
A83: ='1. BRIEFING'!A32 -> 4.3 | B83: ='1. BRIEFING'!B32 -> RELOCAÇÃO DE PONTO DE ESGOTO 100 MM | C83: UN | D83: ='1. BRIEFING'!D32 -> 1 | E83: =F83/D83 -> 193.0854 | F83: =SUM(F84:F88) -> 193.0854
A84: MO | B84: ENCANADOR l INSTALAÇÃO DE PTO DE ESGOTO DE 100MM | C84: UN | D84: 1 | E84: 75 | F84: =(E84*D84)*$D$83 -> 75
A85: MAT | B85: ADESIVO PLASTICO PARA PVC, FRASCO COM 850 GRCR | C85: UN | D85: 0.08 | E85: 2.88 | F85: =(E85*D85)*$D$83 -> 0.2304
A86: MAT | B86: JOELHO PVC SOLD 90G P/ ESG PREDIAL DN 100MM | C86: UN | D86: 1 | E86: 50 | F86: =(E86*D86)*$D$83 -> 50
A87: MAT | B87: TUBO PVC, SOLDÁVEL, 100 MM PARA ESGOTO PREDIAL | C87: M | D87: 2 | E87: 26 | F87: =(E87*D87)*$D$83 -> 52
A88: MAT | B88: LIXA D'AGUA EM FOLHA, GRAO 100 | C88: UN | D88: 0.21 | E88: 7.55 | F88: =(E88*D88)*$D$60 -> 15.855
D89: =F84/D83 -> 75 | E89: MAT | F89: =SUM(F85:F87)/D83 -> 102.2304
A90: ='1. BRIEFING'!A33 -> 4.4 | B90: ='1. BRIEFING'!B33 -> INSTALAÇÃO DE PONTO DE REGISTRO DE GAVETA | C90: UN | D90: ='1. BRIEFING'!D33 -> 1 | E90: =F90/D90 -> 145 | F90: =SUM(F91:F92) -> 145
A91: MO | B91: ENCANADOR l INSTALAÇÃO DE REGISTRO DE GAVETA | C91: UN | D91: 1 | E91: 75 | F91: =(E91*D91)*$D$83 -> 75
A92: MAT | B92: REGISTRO DE GAVETA (GERAL) | C92: UN | D92: 1 | E92: 70 | F92: =(E92*D92)*$D$83 -> 70
D93: =F91/D90 -> 75 | E93: MAT | F93: =SUM(F92)/D90 -> 70
A94: ='1. BRIEFING'!A34 -> 4.5 | B94: ='1. BRIEFING'!B34 -> INSTALAÇÃO DE PONTO DE REGISTRO DE PRESSÃO | C94: ='1. BRIEFING'!C34 -> UN | D94: ='1. BRIEFING'!D34 -> 1 | E94: =F94/D94 -> 145 | F94: =SUM(F95:F96) -> 145
A95: MO | B95: ENCANADOR l INSTALAÇÃO DE REGISTRO DE PRESSÃO | C95: UN | D95: 1 | E95: 75 | F95: =(E95*D95)*$D$83 -> 75
A96: MAT | B96: REGISTRO DE PRESSÃO (CHUVEIROS) | C96: UN | D96: 1 | E96: 70 | F96: =(E96*D96)*$D$83 -> 70
D97: =F95/D94 -> 75 | E97: MAT | F97: =SUM(F96)/D94 -> 70
A98: ='1. BRIEFING'!A35 -> 5 | B98: ='1. BRIEFING'!B35 -> INSTALAÇÃO ELÉTRICA
A99: ='1. BRIEFING'!A36 -> 5.1 | B99: ='1. BRIEFING'!B36 -> INSTALAÇÃO DE INFRAESTRUTURA PARA TOMADA E ILUMINAÇÃO | C99: UN | D99: ='1. BRIEFING'!D36 -> 1 | E99: =F99/D99 -> 57 | F99: =SUM(F100:F102) -> 57
A100: MO | B100: ELETRICISTA l INSTALAÇÃO DE INFRAESTRUTURA PARA TOMADA E ILUMINAÇÃO | C100: UN | D100: 1 | E100: 50 | F100: =(E100*D100)*$D$99 -> 50
...

Sheet 4. PLAN ORÇA
A1: CLIENTE: | L1: SUA LOGO AQUI!
A2: ARQ.:
A3: OBRA:
A4: PLANILHA ORÇAMENTÁRIA l MÃO DE OBRA l MATERIAL l SERVIÇO
A6: ITEM | B6: DESCRIÇÃO DOS SERVIÇOS | C6: UND | D6: QNTD | E6: R$ UNIT | F6: VALOR UNITÁRIO
F7: M.O | G7: MAT | H7: SERVIÇO | I7: TOTAL UNIT | J7: M.O | K7: MAT | L7: SERVIÇO | M7: TOTAL | N7: PREÇO TOTAL
A8: ='1. BRIEFING'!A8 -> 1 | B8: ='1. BRIEFING'!B8 -> SERVIÇOS ADIMINSTRATIVOS | C8: ='1. BRIEFING'!C8 -> 0 | J8: =SUM(J9:J13) -> 0 | K8: =SUM(K9:K13) -> 0 | L8: =SUM(L9:L13) -> 0 | M8: =SUM(M9:M13) -> 0 | N8: =SUM(N9:N13) -> 0 | O8: =N8/$N$92 -> 0
A9: ='1. BRIEFING'!A9 -> 1.1 | B9: ='1. BRIEFING'!B9 -> ADMINISTRAÇÃO DE OBRA | C9: ='1. BRIEFING'!C9 -> MES | D9: ='1. BRIEFING'!D9 -> 1 | E9: =I9 -> 0 | F9: 0 | G9: 0 | H9: 0 | I9: =SUM(F9:H9) -> 0 | J9: =F9*D9 -> 0 | K9: =G9*D9 -> 0 | L9: =H9*D9 -> 0 | M9: =SUM(J9:L9) -> 0 | N9: =M9*(1+$N$96) -> 0
A10: ='1. BRIEFING'!A10 -> 1.2 | B10: ='1. BRIEFING'!B10 -> TRANSPORTE E ALIMENTAÇÃO EQP ADM | C10: ='1. BRIEFING'!C10 -> MES | D10: ='1. BRIEFING'!D10 -> 1 | E10: =I10 -> 0 | F10: 0 | G10: 0 | H10: 0 | I10: =SUM(F10:H10) -> 0 | J10: =F10*D10 -> 0 | K10: =G10*D10 -> 0 | L10: =H10*D10 -> 0 | M10: =SUM(J10:L10) -> 0 | N10: =M10*(1+$N$96) -> 0
A11: ='1. BRIEFING'!A11 -> 1.3 | B11: ='1. BRIEFING'!B11 -> ART DE EXECUÇÃO DA OBRA | C11: ='1. BRIEFING'!C11 -> UN | D11: ='1. BRIEFING'!D11 -> 1 | E11: =I11 -> 0 | F11: 0 | G11: 0 | H11: 0 | I11: =SUM(F11:H11) -> 0 | J11: =F11*D11 -> 0 | K11: =G11*D11 -> 0 | L11: =H11*D11 -> 0 | M11: =SUM(J11:L11) -> 0 | N11: =M11*(1+$N$96) -> 0
A12: ='1. BRIEFING'!A12 -> 1.4 | B12: ='1. BRIEFING'!B12 -> ISOLAMENTO/PROTEÇÃO COM LONA/PLÁSTICO BOLHA | C12: ='1. BRIEFING'!C12 -> VB | D12: ='1. BRIEFING'!D12 -> 1 | E12: =I12 -> 0 | F12: 0 | G12: 0 | H12: 0 | I12: =SUM(F12:H12) -> 0 | J12: =F12*D12 -> 0 | K12: =G12*D12 -> 0 | L12: =H12*D12 -> 0 | M12: =SUM(J12:L12) -> 0 | N12: =M12*(1+$N$96) -> 0
A13: ='1. BRIEFING'!A13 -> 1.5 | B13: ='1. BRIEFING'!B13 -> MOBILIZAÇÃO E DESMOBILIZAÇÃO | C13: ='1. BRIEFING'!C13 -> UN | D13: ='1. BRIEFING'!D13 -> 1 | E13: =I13 -> 0 | F13: 0 | G13: 0 | H13: 0 | I13: =SUM(F13:H13) -> 0 | J13: =F13*D13 -> 0 | K13: =G13*D13 -> 0 | L13: =H13*D13 -> 0 | M13: =SUM(J13:L13) -> 0 | N13: =M13*(1+$N$96) -> 0
A14: ='1. BRIEFING'!A14 -> 2 | B14: ='1. BRIEFING'!B14 -> DEMOLIÇÃO E RETIRADA | J14: =SUM(J15:J23) -> 800 | K14: =SUM(K15:K23) -> 7 | L14: =SUM(L15:L23) -> 400 | M14: =SUM(M15:M23) -> 1207 | N14: =SUM(N15:N23) -> 1609.3333 | O14: =N14/$N$92 -> 0.041793281
A15: ='1. BRIEFING'!A15 -> 2.1 | B15: ='1. BRIEFING'!B15 -> DEMOLIÇÃO DE ALVENARIA DE VEDAÇÃO | C15: ='1. BRIEFING'!C15 -> M² | D15: ='1. BRIEFING'!D15 -> 1,00 | E15: =I15 -> 32.5 | F15: ='3. CPU'!E12 -> 30 | G15: ='3. CPU'!E10 -> 2.5 | H15: 0 | I15: =SUM(F15:H15) -> 32.5 | J15: =F15*D15 -> 30 | K15: =G15*D15 -> 2.5 | L15: =H15*D15 -> 0 | M15: =SUM(J15:L15) -> 32.5 | N15: =M15*(1+$N$96) -> 43.333333
A16: ='1. BRIEFING'!A16 -> 2.2 | B16: ='1. BRIEFING'!B16 -> REMOÇÃO DE BANCADAS EM GRANITO | C16: ='1. BRIEFING'!C16 -> UND | D16: ='1. BRIEFING'!D16 -> 1,00 | E16: =I16 -> 150 | F16: 150 | G16: 0 | H16: 0 | I16: =SUM(F16:H16) -> 150 | J16: =F16*D16 -> 150 | K16: =G16*D16 -> 0 | L16: =H16*D16 -> 0 | M16: =SUM(J16:L16) -> 150 | N16: =M16*(1+$N$96) -> 200
A17: ='1. BRIEFING'!A17 -> 2.3 | B17: ='1. BRIEFING'!B17 -> REMOÇÃO DE LOUÇAS E METAIS | C17: ='1. BRIEFING'!C17 -> VB | D17: ='1. BRIEFING'!D17 -> 1,00 | E17: =I17 -> 350 | F17: 350 | G17: 0 | H17: 0 | I17: =SUM(F17:H17) -> 350 | J17: =F17*D17 -> 350 | K17: =G17*D17 -> 0 | L17: =H17*D17 -> 0 | M17: =SUM(J17:L17) -> 350 | N17: =M17*(1+$N$96) -> 466.66667
A18: ='1. BRIEFING'!A18 -> 2.4 | B18: ='1. BRIEFING'!B18 -> REMOÇÃO DE PORTAS INTERNAS EM MADEIRA | C18: ='1. BRIEFING'!C18 -> UN | D18: ='1. BRIEFING'!D18 -> 1,00 | E18: =I18 -> 75 | F18: 75 | G18: 0 | H18: 0 | I18: =SUM(F18:H18) -> 75 | J18: =F18*D18 -> 75 | K18: =G18*D18 -> 0 | L18: =H18*D18 -> 0 | M18: =SUM(J18:L18) -> 75 | N18: =M18*(1+$N$96) -> 100
A19: ='1. BRIEFING'!A19 -> 2.5 | B19: ='1. BRIEFING'!B19 -> DEMOLIÇÃO DE REVESTIMENTO CERÂMICO EM PAREDE | C19: ='1. BRIEFING'!C19 -> M² | D19: ='1. BRIEFING'!D19 -> 1,00 | E19: =I19 -> 26.5 | F19: 25 | G19: 1.5 | H19: 0 | I19: =SUM(F19:H19) -> 26.5 | J19: =F19*D19 -> 25 | K19: =G19*D19 -> 1.5 | L19: =H19*D19 -> 0 | M19: =SUM(J19:L19) -> 26.5 | N19: =M19*(1+$N$96) -> 35.333333
A20: ='1. BRIEFING'!A20 -> 2.6 | B20: ='1. BRIEFING'!B20 -> DEMOLIÇÃO DE REVESTIMENTO CERÂMICO EM PISO | C20: ='1. BRIEFING'!C20 -> M² | D20: ='1. BRIEFING'!D20 -> 1,00 | E20: =I20 -> 26.5 | F20: 25 | G20: 1.5 | H20: 0 | I20: =SUM(F20:H20) -> 26.5 | J20: =F20*D20 -> 25 | K20: =G20*D20 -> 1.5 | L20: =H20*D20 -> 0 | M20: =SUM(J20:L20) -> 26.5 | N20: =M20*(1+$N$96) -> 35.333333
A21: ='1. BRIEFING'!A21 -> 2.7 | B21: ='1. BRIEFING'!B21 -> DEMOLIÇÃO DE FORRO EM GESSO/PVC | C21: ='1. BRIEFING'!C21 -> M² | D21: ='1. BRIEFING'!D21 -> 1,00 | E21: =I21 -> 11.5 | F21: 10 | G21: 1.5 | H21: 0 | I21: =SUM(F21:H21) -> 11.5 | J21: =F21*D21 -> 10 | K21: =G21*D21 -> 1.5 | L21: =H21*D21 -> 0 | M21: =SUM(J21:L21) -> 11.5 | N21: =M21*(1+$N$96) -> 15.333333
A22: ='1. BRIEFING'!A22 -> 2.8 | B22: ='1. BRIEFING'!B22 -> REMOÇÃO DE LUMINÁRIAS INTERNAS (FORRO) | C22: ='1. BRIEFING'!C22 -> UN | D22: ='1. BRIEFING'!D22 -> 1,00 | E22: =I22 -> 15 | F22: 15 | G22: 0 | H22: 0 | I22: =SUM(F22:H22) -> 15 | J22: =F22*D22 -> 15 | K22: =G22*D22 -> 0 | L22: =H22*D22 -> 0 | M22: =SUM(J22:L22) -> 15 | N22: =M22*(1+$N$96) -> 20
A23: ='1. BRIEFING'!A23 -> 2.9 | B23: ='1. BRIEFING'!B23 -> REMOÇÃO DOS ENTULHOS POR SACOS E CARRO PEQUENO | C23: ='1. BRIEFING'!C23 -> UN | D23: ='1. BRIEFING'!D23 -> 1,00 | E23: =I23 -> 520 | F23: 120 | G23: 0 | H23: 400 | I23: =SUM(F23:H23) -> 520 | J23: =F23*D23 -> 120 | K23: =G23*D23 -> 0 | L23: =H23*D23 -> 400 | M23: =SUM(J23:L23) -> 520 | N23: =M23*(1+$N$96) -> 693.33333
A24: ='1. BRIEFING'!A24 -> 3 | B24: ='1. BRIEFING'!B24 -> SERVIÇO EM ALVENARIA | J24: =SUM(J25) -> 30 | K24: =SUM(K25) -> 40.28 | L24: =SUM(L25) -> 0 | M24: =SUM(M25) -> 70.28 | N24: =SUM(N25) -> 93.706667 | O24: =N24/$N$92 -> 0.0024334978
A25: ='1. BRIEFING'!A25 -> 3.1 | B25: ='1. BRIEFING'!B25 -> ASSENTAMENTO DE ALVENARIA DE VEDAÇÃO | C25: ='1. BRIEFING'!C25 -> M² | D25: ='1. BRIEFING'!D25 -> 1 | E25: =I25 -> 70.28 | F25: 30 | G25: 40.28 | H25: 0 | I25: =SUM(F25:H25) -> 70.28 | J25: =F25*D25 -> 30 | K25: =G25*D25 -> 40.28 | L25: =H25*D25 -> 0 | M25: =SUM(J25:L25) -> 70.28 | N25: =M25*(1+$N$96) -> 93.706667
A26: ='1. BRIEFING'!A29 -> 4 | B26: ='1. BRIEFING'!B29 -> INSTALAÇÃO HIDRÁULICA | J26: =SUM(J27:J31) -> 530 | K26: =SUM(K27:K31) -> 274.33 | L26: =SUM(L27:L31) -> 0 | M26: =SUM(M27:M31) -> 804.33 | N26: =SUM(N27:N31) -> 1072.44 | O26: =N26/$N$92 -> 0.02785053
A27: ='1. BRIEFING'!A30 -> 4.1 | B27: ='1. BRIEFING'!B30 -> INSTALAÇAO DE PONTO DE ÁGUA FRIA | C27: ='1. BRIEFING'!C30 -> UN | D27: ='1. BRIEFING'!D30 -> 10 | E27: =I27 -> 48.5 | F27: 40 | G27: 8.5 | H27: 0 | I27: =SUM(F27:H27) -> 48.5 | J27: =F27*D27 -> 400 | K27: =G27*D27 -> 85 | L27: =H27*D27 -> 0 | M27: =SUM(J27:L27) -> 485 | N27: =M27*(1+$N$96) -> 646.66667
A28: ='1. BRIEFING'!A31 -> 4.2 | B28: ='1. BRIEFING'!B31 -> INSTALAÇÃO DE PONTO DE ESGOTO 50 MM | C28: ='1. BRIEFING'!C31 -> UN | D28: ='1. BRIEFING'!D31 -> 1 | E28: =I28 -> 104.19 | F28: 30 | G28: 74.19 | H28: 0 | I28: =SUM(F28:H28) -> 104.19 | J28: =F28*D28 -> 30 | K28: =G28*D28 -> 74.19 | L28: =H28*D28 -> 0 | M28: =SUM(J28:L28) -> 104.19 | N28: =M28*(1+$N$96) -> 138.92
A29: ='1. BRIEFING'!A32 -> 4.3 | B29: ='1. BRIEFING'!B32 -> RELOCAÇÃO DE PONTO DE ESGOTO 100 MM | C29: ='1. BRIEFING'!C32 -> UN | D29: ='1. BRIEFING'!D32 -> 1 | E29: =I29 -> 50.7 | F29: 30 | G29: 20.7 | H29: 0 | I29: =SUM(F29:H29) -> 50.7 | J29: =F29*D29 -> 30 | K29: =G29*D29 -> 20.7 | L29: =H29*D29 -> 0 | M29: =SUM(J29:L29) -> 50.7 | N29: =M29*(1+$N$96) -> 67.6
A30: ='1. BRIEFING'!A33 -> 4.4 | B30: ='1. BRIEFING'!B33 -> INSTALAÇÃO DE PONTO DE REGISTRO DE GAVETA | C30: ='1. BRIEFING'!C33 -> UN | D30: ='1. BRIEFING'!D33 -> 1 | E30: =I30 -> 82.22 | F30: 35 | G30: 47.22 | H30: 0 | I30: =SUM(F30:H30) -> 82.22 | J30: =F30*D30 -> 35 | K30: =G30*D30 -> 47.22 | L30: =H30*D30 -> 0 | M30: =SUM(J30:L30) -> 82.22 | N30: =M30*(1+$N$96) -> 109.62667
A31: ='1. BRIEFING'!A34 -> 4.5 | B31: ='1. BRIEFING'!B34 -> INSTALAÇÃO DE PONTO DE REGISTRO DE PRESSÃO | C31: ='1. BRIEFING'!C34 -> UN | D31: ='1. BRIEFING'!D34 -> 1 | E31: =I31 -> 82.22 | F31: 35 | G31: 47.22 | H31: 0 | I31: =SUM(F31:H31) -> 82.22 | J31: =F31*D31 -> 35 | K31: =G31*D31 -> 47.22 | L31: =H31*D31 -> 0 | M31: =SUM(J31:L31) -> 82.22 | N31: =M31*(1+$N$96) -> 109.62667
A32: ='1. BRIEFING'!A35 -> 5 | B32: ='1. BRIEFING'!B35 -> INSTALAÇÃO ELÉTRICA | J32: =SUM(J33:J37) -> 175 | K32: =SUM(K33:K37) -> 0 | L32: =SUM(L33:L37) -> 0 | M32: =SUM(M33:M37) -> 175 | N32: =SUM(N33:N37) -> 233.33333 | O32: =N32/$N$92 -> 0.0060595064
A33: ='1. BRIEFING'!A36 -> 5.1 | B33: ='1. BRIEFING'!B36 -> INSTALAÇÃO DE INFRAESTRUTURA PARA TOMADA E ILUMINAÇÃO | C33: ='1. BRIEFING'!C36 -> UN | D33: ='1. BRIEFING'!D36 -> 1 | E33: =I33 -> 35 | F33: 35 | G33: 0 | H33: 0 | I33: =SUM(F33:H33) -> 35 | J33: =F33*D33 -> 35 | K33: =G33*D33 -> 0 | L33: =H33*D33 -> 0 | M33: =SUM(J33:L33) -> 35 | N33: =M33*(1+$N$96) -> 46.666667
A34: ='1. BRIEFING'!A37 -> 5.2 | B34: ='1. BRIEFING'!B37 -> INSTALAÇÃO DE CABEAMENTO PARA PONTOS DE TOMADAS | C34: ='1. BRIEFING'!C37 -> UN | D34: ='1. BRIEFING'!D37 -> 1 | E34: =I34 -> 35 | F34: 35 | G34: 0 | H34: 0 | I34: =SUM(F34:H34) -> 35 | J34: =F34*D34 -> 35 | K34: =G34*D34 -> 0 | L34: =H34*D34 -> 0 | M34: =SUM(J34:L34) -> 35 | N34: =M34*(1+$N$96) -> 46.666667
A35: ='1. BRIEFING'!A38 -> 5.3 | B35: ='1. BRIEFING'!B38 -> INSTALAÇÃO DE CABEAMENTO PARA PONTOS DE ILUMINAÇÃO | C35: ='1. BRIEFING'!C38 -> UN | D35: ='1. BRIEFING'!D38 -> 1 | E35: =I35 -> 35 | F35: 35 | G35: 0 | H35: 0 | I35: =SUM(F35:H35) -> 35 | J35: =F35*D35 -> 35 | K35: =G35*D35 -> 0 | L35: =H35*D35 -> 0 | M35: =SUM(J35:L35) -> 35 | N35: =M35*(1+$N$96) -> 46.666667
A36: ='1. BRIEFING'!A39 -> 5.4 | B36: ='1. BRIEFING'!B39 -> REISNTALAÇÃO DE QUADRO DE DISTRIBUIÇÃO (ADEQUAÇÃO) | C36: ='1. BRIEFING'!C39 -> VB | D36: ='1. BRIEFING'!D39 -> 1 | E36: =I36 -> 35 | F36: 35 | G36: 0 | H36: 0 | I36: =SUM(F36:H36) -> 35 | J36: =F36*D36 -> 35 | K36: =G36*D36 -> 0 | L36: =H36*D36 -> 0 | M36: =SUM(J36:L36) -> 35 | N36: =M36*(1+$N$96) -> 46.666667
A37: ='1. BRIEFING'!A40 -> 5.5 | B37: ='1. BRIEFING'!B40 -> INSTALAÇÃO DE INFRAESTRUTURA PARA PONTOS DE REDE/ANTENA/CAMERA/SOM | C37: ='1. BRIEFING'!C40 -> UN | D37: ='1. BRIEFING'!D40 -> 1 | E37: =I37 -> 35 | F37: 35 | G37: 0 | H37: 0 | I37: =SUM(F37:H37) -> 35 | J37: =F37*D37 -> 35 | K37: =G37*D37 -> 0 | L37: =H37*D37 -> 0 | M37: =SUM(J37:L37) -> 35 | N37: =M37*(1+$N$96) -> 46.666667
A38: ='1. BRIEFING'!A41 -> 6 | B38: ='1. BRIEFING'!B41 -> INSTALAÇÃO DE EQUIPAMENTOS | J38: =SUM(J39:J41) -> 250 | K38: =SUM(K39:K41) -> 125.63 | L38: =SUM(L39:L41) -> 0 | M38: =SUM(M39:M41) -> 375.63 | N38: =SUM(N39:N41) -> 500.84 | O38: =N38/$N$92 -> 0.013006471
A39: ='1. BRIEFING'!A42 -> 6.1 | B39: ='1. BRIEFING'!B42 -> INSTALAÇÃO DE INFRA PARA AR CONDICIONADO | C39: ='1. BRIEFING'!C42 -> UN | D39: ='1. BRIEFING'!D42 -> 1 | E39: =I39 -> 94.43 | F39: 50 | G39: 44.43 | H39: 0 | I39: =SUM(F39:H39) -> 94.43 | J39: =F39*D39 -> 50 | K39: =G39*D39 -> 44.43 | L39: =H39*D39 -> 0 | M39: =SUM(J39:L39) -> 94.43 | N39: =M39*(1+$N$96) -> 125.90667
A40: ='1. BRIEFING'!A43 -> 6.2 | B40: ='1. BRIEFING'!B43 -> INSTALAÇÃO DE BOILER | C40: ='1. BRIEFING'!C43 -> UN | D40: ='1. BRIEFING'!D43 -> 1 | E40: =I40 -> 131.2 | F40: 50 | G40: 81.2 | H40: 0 | I40: =SUM(F40:H40) -> 131.2 | J40: =F40*D40 -> 50 | K40: =G40*D40 -> 81.2 | L40: =H40*D40 -> 0 | M40: =SUM(J40:L40) -> 131.2 | N40: =M40*(1+$N$96) -> 174.93333
A41: ='1. BRIEFING'!A44 -> 6.3 | B41: ='1. BRIEFING'!B44 -> INSTALAÇÃO DE EXAUSTOR l BWC CAMARIM E MAS | C41: ='1. BRIEFING'!C44 -> UN | D41: ='1. BRIEFING'!D44 -> 1 | E41: =I41 -> 150 | F41: 150 | G41: 0 | H41: 0 | I41: =SUM(F41:H41) -> 150 | J41: =F41*D41 -> 150 | K41: =G41*D41 -> 0 | L41: =H41*D41 -> 0 | M41: =SUM(J41:L41) -> 150 | N41: =M41*(1+$N$96) -> 200
A42: ='1. BRIEFING'!A45 -> 7 | B42: ='1. BRIEFING'!B45 -> INSTALAÇÃO DE ILUMINAÇÃO | J42: =SUM(J43:J46) -> 300 | K42: =SUM(K43:K46) -> 0 | L42: =SUM(L43:L46) -> 6300 | M42: =SUM(M43:M46) -> 6600 | N42: =SUM(N43:N46) -> 8800 | O42: =N42/$N$92 -> 0.22852996
A43: ='1. BRIEFING'!A46 -> 7.1 | B43: ='1. BRIEFING'!B46 -> INSTALAÇÃO DE LUMINÁRIA DE EMBUTIR QUADRADA 20W EM FORRO DE GESSO | C43: ='1. BRIEFING'!C46 -> UN | D43: ='1. BRIEFING'!D46 -> 1 | E43: =I43 -> 150 | F43: 150 | G43: 0 | H43: 0 | I43: =SUM(F43:H43) -> 150 | J43: =F43*D43 -> 150 | K43: =G43*D43 -> 0 | L43: =H43*D43 -> 0 | M43: =SUM(J43:L43) -> 150 | N43: =M43*(1+$N$96) -> 200
A44: ='1. BRIEFING'!A47 -> 7.2 | B44: ='1. BRIEFING'!B47 -> INSTALAÇÃO DE DICROICAS DIRECIONAIS | C44: ='1. BRIEFING'!C47 -> UN | D44: ='1. BRIEFING'!D47 -> 1 | E44: =I44 -> 150 | F44: 150 | G44: 0 | H44: 0 | I44: =SUM(F44:H44) -> 150 | J44: =F44*D44 -> 150 | K44: =G44*D44 -> 0 | L44: =H44*D44 -> 0 | M44: =SUM(J44:L44) -> 150 | N44: =M44*(1+$N$96) -> 200
A45: ='1. BRIEFING'!A48 -> 7.3 | B45: ='1. BRIEFING'!B48 -> INSTALAÇÃO DE FITA EM LED | C45: ='1. BRIEFING'!C48 -> UN | D45: ='1. BRIEFING'!D48 -> 1 | E45: =I45 -> 5500 | F45: 0 | G45: 0 | H45: 5500 | I45: =SUM(F45:H45) -> 5500 | J45: =F45*D45 -> 0 | K45: =G45*D45 -> 0 | L45: =H45*D45 -> 5500 | M45: =SUM(J45:L45) -> 5500 | N45: =M45*(1+$N$96) -> 7333.3333
A46: ='1. BRIEFING'!A49 -> 7.4 | B46: ='1. BRIEFING'!B49 -> INSTALAÇÃO DE PENDENTE | C46: ='1. BRIEFING'!C49 -> UN | D46: ='1. BRIEFING'!D49 -> 1 | E46: =I46 -> 800 | F46: 0 | G46: 0 | H46: 800 | I46: =SUM(F46:H46) -> 800 | J46: =F46*D46 -> 0 | K46: =G46*D46 -> 0 | L46: =H46*D46 -> 800 | M46: =SUM(J46:L46) -> 800 | N46: =M46*(1+$N$96) -> 1066.6667
A47: ='1. BRIEFING'!A54 -> 8 | B47: ='1. BRIEFING'!B54 -> SERVIÇO EM FORRO | J47: =SUM(J48:J51) -> 0 | K47: =SUM(K48:K51) -> 0 | L47: =SUM(L48:L51) -> 135 | M47: =SUM(M48:M51) -> 135 | N47: =SUM(N48:N51) -> 180 | O47: =N47/$N$92 -> 0.0046744764
A48: ='1. BRIEFING'!A55 -> 8.1 | B48: ='1. BRIEFING'!B55 -> FORNECIMENTO E INSTALAÇÃO DE FORRO EM GESSO | C48: ='1. BRIEFING'!C55 -> M² | D48: ='1. BRIEFING'!D55 -> 1 | E48: =I48 -> 35 | F48: 0 | G48: 0 | H48: 35 | I48: =SUM(F48:H48) -> 35 | J48: =F48*D48 -> 0 | K48: =G48*D48 -> 0 | L48: =H48*D48 -> 35 | M48: =SUM(J48:L48) -> 35 | N48: =M48*(1+$N$96) -> 46.666667
A49: ='1. BRIEFING'!A56 -> 8.2 | B49: ='1. BRIEFING'!B56 -> FORNECIMENTO E INSTALAÇÃO DE JUNTA EM DILATAÇÃO 3X3 CM | C49: ='1. BRIEFING'!C56 -> M | D49: ='1. BRIEFING'!D56 -> 1 | E49: =I49 -> 60 | F49: 0 | G49: 0 | H49: 60 | I49: =SUM(F49:H49) -> 60 | J49: =F49*D49 -> 0 | K49: =G49*D49 -> 0 | L49: =H49*D49 -> 60 | M49: =SUM(J49:L49) -> 60 | N49: =M49*(1+$N$96) -> 80
A50: ='1. BRIEFING'!A57 -> 8.3 | B50: ='1. BRIEFING'!B57 -> FORNECIMENTO E INSTALAÇÃO DE CORTINEIRO | C50: ='1. BRIEFING'!C57 -> M | D50: ='1. BRIEFING'!D57 -> 1 | E50: =I50 -> 20 | F50: 0 | G50: 0 | H50: 20 | I50: =SUM(F50:H50) -> 20 | J50: =F50*D50 -> 0 | K50: =G50*D50 -> 0 | L50: =H50*D50 -> 20 | M50: =SUM(J50:L50) -> 20 | N50: =M50*(1+$N$96) -> 26.666667
A51: ='1. BRIEFING'!A58 -> 8.4 | B51: ='1. BRIEFING'!B58 -> FORNECIMENTO E INSTALAÇÃO DE SANCAS | C51: ='1. BRIEFING'!C58 -> M | D51: ='1. BRIEFING'!D58 -> 1 | E51: =I51 -> 20 | F51: 0 | G51: 0 | H51: 20 | I51: =SUM(F51:H51) -> 20 | J51: =F51*D51 -> 0 | K51: =G51*D51 -> 0 | L51: =H51*D51 -> 20 | M51: =SUM(J51:L51) -> 20 | N51: =M51*(1+$N$96) -> 26.666667
A52: ='1. BRIEFING'!A59 -> 9 | B52: ='1. BRIEFING'!B59 -> SERVIÇO EM ESQUADRIA DE MADEIRA | J52: =SUM(J53:J58) -> 0 | K52: =SUM(K53:K58) -> 0 | L52: =SUM(L53:L58) -> 13440 | M52: =SUM(M53:M58) -> 13440 | N52: =SUM(N53:N58) -> 17920 | O52: =N52/$N$92 -> 0.46537009
A53: ='1. BRIEFING'!A60 -> 9.1 | B53: ='1. BRIEFING'!B60 -> FORNECIMENTO E INSTALAÇÃO DE PORTA EM MADEIRA 0,60 x 2,10 m l COMPLETA | C53: ='1. BRIEFING'!C60 -> UN | D53: ='1. BRIEFING'!D60 -> 1 | E53: =I53 -> 2240 | F53: 0 | G53: 0 | H53: 2240 | I53: =SUM(F53:H53) -> 2240 | J53: =F53*D53 -> 0 | K53: =G53*D53 -> 0 | L53: =H53*D53 -> 2240 | M53: =SUM(J53:L53) -> 2240 | N53: =M53*(1+$N$96) -> 2986.6667
A54: ='1. BRIEFING'!A61 -> 9.2 | B54: ='1. BRIEFING'!B61 -> FORNECIMENTO E INSTALAÇÃO DE PORTA EM MADEIRA 0,70 X 2,10 M l COMPLETA | C54: ='1. BRIEFING'!C61 -> UN | D54: ='1. BRIEFING'!D61 -> 1 | E54: =I54 -> 2240 | F54: 0 | G54: 0 | H54: 2240 | I54: =SUM(F54:H54) -> 2240 | J54: =F54*D54 -> 0 | K54: =G54*D54 -> 0 | L54: =H54*D54 -> 2240 | M54: =SUM(J54:L54) -> 2240 | N54: =M54*(1+$N$96) -> 2986.6667
A55: ='1. BRIEFING'!A62 -> 9.3 | B55: ='1. BRIEFING'!B62 -> FORNECIMENTO E INSTALAÇÃO DE PORTA EM MADEIRA 0,80 X 2,10 M l COMPLETA | C55: ='1. BRIEFING'!C62 -> UN | D55: ='1. BRIEFING'!D62 -> 1 | E55: =I55 -> 2240 | F55: 0 | G55: 0 | H55: 2240 | I55: =SUM(F55:H55) -> 2240 | J55: =F55*D55 -> 0 | K55: =G55*D55 -> 0 | L55: =H55*D55 -> 2240 | M55: =SUM(J55:L55) -> 2240 | N55: =M55*(1+$N$96) -> 2986.6667
A56: ='1. BRIEFING'!A63 -> 9.4 | B56: ='1. BRIEFING'!B63 -> FORNECIMENTO E INSTALAÇÃO DE PORTA EM MADEIRA 0,90 X 2,10 M l COMPLETA | C56: ='1. BRIEFING'!C63 -> UN | D56: ='1. BRIEFING'!D63 -> 1 | E56: =I56 -> 2240 | F56: 0 | G56: 0 | H56: 2240 | I56: =SUM(F56:H56) -> 2240 | J56: =F56*D56 -> 0 | K56: =G56*D56 -> 0 | L56: =H56*D56 -> 2240 | M56: =SUM(J56:L56) -> 2240 | N56: =M56*(1+$N$96) -> 2986.6667
A57: ='1. BRIEFING'!A64 -> 9.5 | B57: ='1. BRIEFING'!B64 -> FORNECIMENTO E INSTALAÇÃO DE PORTA EM MADEIRA 0,90 X 2,10 M l COMPLETA | C57: ='1. BRIEFING'!C64 -> UN | D57: ='1. BRIEFING'!D64 -> 1 | E57: =I57 -> 2240 | F57: 0 | G57: 0 | H57: 2240 | I57: =SUM(F57:H57) -> 2240 | J57: =F57*D57 -> 0 | K57: =G57*D57 -> 0 | L57: =H57*D57 -> 2240 | M57: =SUM(J57:L57) -> 2240 | N57: =M57*(1+$N$96) -> 2986.6667
A58: ='1. BRIEFING'!A65 -> 9.6 | B58: ='1. BRIEFING'!B65 -> FORNECIMENTO E INSTALAÇÃO DE PORTA EM MADEIRA 0,90 X 2,10 M l COMPLETA | C58: ='1. BRIEFING'!C65 -> UN | D58: ='1. BRIEFING'!D65 -> 1 | E58: =I58 -> 2240 | F58: 0 | G58: 0 | H58: 2240 | I58: =SUM(F58:H58) -> 2240 | J58: =F58*D58 -> 0 | K58: =G58*D58 -> 0 | L58: =H58*D58 -> 2240 | M58: =SUM(J58:L58) -> 2240 | N58: =M58*(1+$N$96) -> 2986.6667
A59: ='1. BRIEFING'!A66 -> 10 | B59: ='1. BRIEFING'!B66 -> SERVIÇO DE MARMORARIA | J59: =SUM(J60:J63) -> 0 | K59: =SUM(K60:K63) -> 0 | L59: =SUM(L60:L63) -> 3000 | M59: =SUM(M60:M63) -> 3000 | N59: =SUM(N60:N63) -> 4000 | O59: =N59/$N$92 -> 0.10387725
A60: ='1. BRIEFING'!A67 -> 10.1 | B60: ='1. BRIEFING'!B67 -> FORNECIMENTO E INSTALAÇÃO DE BANCADA EM GRANITO | C60: ='1. BRIEFING'!C67 -> VB | D60: ='1. BRIEFING'!D67 -> 1 | E60: =I60 -> 1500 | F60: 0 | G60: 0 | H60: 1500 | I60: =SUM(F60:H60) -> 1500 | J60: =F60*D60 -> 0 | K60: =G60*D60 -> 0 | L60: =H60*D60 -> 1500 | M60: =SUM(J60:L60) -> 1500 | N60: =M60*(1+$N$96) -> 2000
A61: ='1. BRIEFING'!A68 -> 10.2 | B61: ='1. BRIEFING'!B68 -> FORNECIMENTO E INSTALAÇÃO DE NICHO EM GRANITO | C61: ='1. BRIEFING'!C68 -> VB | D61: ='1. BRIEFING'!D68 -> 1 | E61: =I61 -> 500 | F61: 0 | G61: 0 | H61: 500 | I61: =SUM(F61:H61) -> 500 | J61: =F61*D61 -> 0 | K61: =G61*D61 -> 0 | L61: =H61*D61 -> 500 | M61: =SUM(J61:L61) -> 500 | N61: =M61*(1+$N$96) -> 666.66667
A62: ='1. BRIEFING'!A69 -> 10.3 | B62: ='1. BRIEFING'!B69 -> FORNECIMENTO E INSTALAÇÃO DE DIVBOX EM GRANITO | C62: ='1. BRIEFING'!C69 -> VB | D62: ='1. BRIEFING'!D69 -> 1 | E62: =I62 -> 500 | F62: 0 | G62: 0 | H62: 500 | I62: =SUM(F62:H62) -> 500 | J62: =F62*D62 -> 0 | K62: =G62*D62 -> 0 | L62: =H62*D62 -> 500 | M62: =SUM(J62:L62) -> 500 | N62: =M62*(1+$N$96) -> 666.66667
A63: ='1. BRIEFING'!A70 -> 10.4 | B63: ='1. BRIEFING'!B70 -> FORNECIMENTO E INSTALAÇÃO DE NICHO EM GRANITO | C63: ='1. BRIEFING'!C70 -> VB | D63: ='1. BRIEFING'!D70 -> 1 | E63: =I63 -> 500 | F63: 0 | G63: 0 | H63: 500 | I63: =SUM(F63:H63) -> 500 | J63: =F63*D63 -> 0 | K63: =G63*D63 -> 0 | L63: =H63*D63 -> 500 | M63: =SUM(J63:L63) -> 500 | N63: =M63*(1+$N$96) -> 666.66667
A64: ='1. BRIEFING'!A71 -> 11 | B64: ='1. BRIEFING'!B71 -> REVESTIMENTO EM ARGAMASSA | J64: =SUM(J65:J67) -> 150 | K64: =SUM(K65:K67) -> 63 | L64: =SUM(L65:L67) -> 0 | M64: =SUM(M65:M67) -> 213 | N64: =SUM(N65:N67) -> 284 | O64: =N64/$N$92 -> 0.007375285
A65: ='1. BRIEFING'!A72 -> 11.1 | B65: ='1. BRIEFING'!B72 -> APLICAÇÃO DE CHAPISCO E REBOCO EM PAREDE DE ALVENARIA NOVA | C65: ='1. BRIEFING'!C72 -> M² | D65: ='1. BRIEFING'!D72 -> 1 | E65: =I65 -> 71 | F65: 50 | G65: 21 | H65: 0 | I65: =SUM(F65:H65) -> 71 | J65: =F65*D65 -> 50 | K65: =G65*D65 -> 21 | L65: =H65*D65 -> 0 | M65: =SUM(J65:L65) -> 71 | N65: =M65*(1+$N$96) -> 94.666667
A66: ='1. BRIEFING'!A73 -> 11.2 | B66: ='1. BRIEFING'!B73 -> REGULARIZAÇÃO COM REBOCO FINO PARA RECEBIMENTO DE REVESTIMENTO NOVO | C66: ='1. BRIEFING'!C73 -> M² | D66: ='1. BRIEFING'!D73 -> 1 | E66: =I66 -> 71 | F66: 50 | G66: 21 | H66: 0 | I66: =SUM(F66:H66) -> 71 | J66: =F66*D66 -> 50 | K66: =G66*D66 -> 21 | L66: =H66*D66 -> 0 | M66: =SUM(J66:L66) -> 71 | N66: =M66*(1+$N$96) -> 94.666667
A67: ='1. BRIEFING'!A74 -> 11.3 | B67: ='1. BRIEFING'!B74 -> REGULARIZAÇÃO DE PISO COM ATÉ 5 CM PARA RECEBIMENTO DE REVESTIMENTO NONO | C67: ='1. BRIEFING'!C74 -> M² | D67: ='1. BRIEFING'!D74 -> 1 | E67: =I67 -> 71 | F67: 50 | G67: 21 | H67: 0 | I67: =SUM(F67:H67) -> 71 | J67: =F67*D67 -> 50 | K67: =G67*D67 -> 21 | L67: =H67*D67 -> 0 | M67: =SUM(J67:L67) -> 71 | N67: =M67*(1+$N$96) -> 94.666667
A68: ='1. BRIEFING'!A75 -> 12 | B68: ='1. BRIEFING'!B75 -> REVESTIMENTO EM PORCELANATO | C68: ='1. BRIEFING'!C75 -> 0 | J68: =SUM(J69:J74) -> 300 | K68: =SUM(K69:K74) -> 300 | L68: =SUM(L69:L74) -> 0 | M68: =SUM(M69:M74) -> 600 | N68: =SUM(N69:N74) -> 800
A69: ='1. BRIEFING'!A76 -> 12.1 | B69: ='1. BRIEFING'!B76 -> REVESTIMENTO EM PISO ÁREA COMUM l BIANCOGRÉS CRISTALLO 60X60 CM | C69: ='1. BRIEFING'!C76 -> M² | D69: ='1. BRIEFING'!D76 -> 1 | E69: =I69 -> 100 | F69: 50 | G69: 50 | H69: 0 | I69: =SUM(F69:H69) -> 100 | J69: =F69*D69 -> 50 | K69: =G69*D69 -> 50 | L69: =H69*D69 -> 0 | M69: =SUM(J69:L69) -> 100 | N69: =M69*(1+$N$96) -> 133.33333
A70: ='1. BRIEFING'!A77 -> 12.2 | B70: ='1. BRIEFING'!B77 -> REVESTIMENTO EM PISO ÁREA MOLHADA l BIANCOGRÉS CRISTALLO 60X60 CM | C70: ='1. BRIEFING'!C77 -> M² | D70: ='1. BRIEFING'!D77 -> 1 | E70: =I70 -> 100 | F70: 50 | G70: 50 | H70: 0 | I70: =SUM(F70:H70) -> 100 | J70: =F70*D70 -> 50 | K70: =G70*D70 -> 50 | L70: =H70*D70 -> 0 | M70: =SUM(J70:L70) -> 100 | N70: =M70*(1+$N$96) -> 133.33333 | O70: =N70/$N$92 -> 0.0034625751
A71: ='1. BRIEFING'!A78 -> 12.3 | B71: ='1. BRIEFING'!B78 -> REVESTIMENTO EM PAREDE COZINHA l POINTER 60X60 CM | C71: ='1. BRIEFING'!C78 -> M² | D71: ='1. BRIEFING'!D78 -> 1 | E71: =I71 -> 100 | F71: 50 | G71: 50 | H71: 0 | I71: =SUM(F71:H71) -> 100 | J71: =F71*D71 -> 50 | K71: =G71*D71 -> 50 | L71: =H71*D71 -> 0 | M71: =SUM(J71:L71) -> 100 | N71: =M71*(1+$N$96) -> 133.33333
A72: ='1. BRIEFING'!A79 -> 12.4 | B72: ='1. BRIEFING'!B79 -> REVESTIMENTO EM PAREDE BANHEIROS l POINTER 60X60 CM | C72: ='1. BRIEFING'!C79 -> M² | D72: ='1. BRIEFING'!D79 -> 1 | E72: =I72 -> 100 | F72: 50 | G72: 50 | H72: 0 | I72: =SUM(F72:H72) -> 100 | J72: =F72*D72 -> 50 | K72: =G72*D72 -> 50 | L72: =H72*D72 -> 0 | M72: =SUM(J72:L72) -> 100 | N72: =M72*(1+$N$96) -> 133.33333
A73: ='1. BRIEFING'!A80 -> 12.5 | B73: ='1. BRIEFING'!B80 -> REVESTIMENTO EM PAREDE ÁREA DE SERVIÇO l POINTER 60X60 CM | C73: ='1. BRIEFING'!C80 -> M² | D73: ='1. BRIEFING'!D80 -> 1 | E73: =I73 -> 100 | F73: 50 | G73: 50 | H73: 0 | I73: =SUM(F73:H73) -> 100 | J73: =F73*D73 -> 50 | K73: =G73*D73 -> 50 | L73: =H73*D73 -> 0 | M73: =SUM(J73:L73) -> 100 | N73: =M73*(1+$N$96) -> 133.33333
A74: ='1. BRIEFING'!A81 -> 12.6 | B74: ='1. BRIEFING'!B81 -> REVESTIMENTO EM PAREDE VARANDA l POINTER 60X60 CM | C74: ='1. BRIEFING'!C81 -> M² | D74: ='1. BRIEFING'!D81 -> 1 | E74: =I74 -> 100 | F74: 50 | G74: 50 | H74: 0 | I74: =SUM(F74:H74) -> 100 | J74: =F74*D74 -> 50 | K74: =G74*D74 -> 50 | L74: =H74*D74 -> 0 | M74: =SUM(J74:L74) -> 100 | N74: =M74*(1+$N$96) -> 133.33333
A75: ='1. BRIEFING'!A82 -> 13 | B75: ='1. BRIEFING'!B82 -> LOUÇAS E METAIS | C75: ='1. BRIEFING'!C82 -> 0 | J75: =SUM(J76:J81) -> 300 | K75: =SUM(K76:K81) -> 300 | L75: =SUM(L76:L81) -> 0 | M75: =SUM(M76:M81) -> 600 | N75: =SUM(N76:N81) -> 800
A76: ='1. BRIEFING'!A83 -> 13.1 | B76: ='1. BRIEFING'!B83 -> INSTALAÇÃO DE VASO SANITÁRIO COM CX ACOPLADA l ECOLUS CELITE BRANCA | C76: ='1. BRIEFING'!C83 -> UN | D76: ='1. BRIEFING'!D83 -> 1 | E76: =I76 -> 100 | F76: 50 | G76: 50 | H76: 0 | I76: =SUM(F76:H76) -> 100 | J76: =F76*D76 -> 50 | K76: =G76*D76 -> 50 | L76: =H76*D76 -> 0 | M76: =SUM(J76:L76) -> 100 | N76: =M76*(1+$N$96) -> 133.33333
A77: ='1. BRIEFING'!A84 -> 13.2 | B77: ='1. BRIEFING'!B84 -> INSTALAÇÃO DE CUBA SUSPENSA DE CANTO EM LOUÇA BRANCA l CELITE | C77: ='1. BRIEFING'!C84 -> UN | D77: ='1. BRIEFING'!D84 -> 1 | E77: =I77 -> 100 | F77: 50 | G77: 50 | H77: 0 | I77: =SUM(F77:H77) -> 100 | J77: =F77*D77 -> 50 | K77: =G77*D77 -> 50 | L77: =H77*D77 -> 0 | M77: =SUM(J77:L77) -> 100 | N77: =M77*(1+$N$96) -> 133.33333
A78: ='1. BRIEFING'!A85 -> 13.3 | B78: ='1. BRIEFING'!B85 -> INSTALAÇÃO DE TORNEIRA BICA ALTA | C78: ='1. BRIEFING'!C85 -> UN | D78: ='1. BRIEFING'!D85 -> 1 | E78: =I78 -> 100 | F78: 50 | G78: 50 | H78: 0 | I78: =SUM(F78:H78) -> 100 | J78: =F78*D78 -> 50 | K78: =G78*D78 -> 50 | L78: =H78*D78 -> 0 | M78: =SUM(J78:L78) -> 100 | N78: =M78*(1+$N$96) -> 133.33333
A79: ='1. BRIEFING'!A86 -> 13.4 | B79: ='1. BRIEFING'!B86 -> INSTALAÇÃO DE PORTA ACESSÓRIOS l KIT BANHEIRO | C79: ='1. BRIEFING'!C86 -> UN | D79: ='1. BRIEFING'!D86 -> 1 | E79: =I79 -> 100 | F79: 50 | G79: 50 | H79: 0 | I79: =SUM(F79:H79) -> 100 | J79: =F79*D79 -> 50 | K79: =G79*D79 -> 50 | L79: =H79*D79 -> 0 | M79: =SUM(J79:L79) -> 100 | N79: =M79*(1+$N$96) -> 133.33333
A80: ='1. BRIEFING'!A87 -> 13.5 | B80: ='1. BRIEFING'!B87 -> INSTALAÇÃO DE DUCHA HIGIÊNCIA | C80: ='1. BRIEFING'!C87 -> UN | D80: ='1. BRIEFING'!D87 -> 1 | E80: =I80 -> 100 | F80: 50 | G80: 50 | H80: 0 | I80: =SUM(F80:H80) -> 100 | J80: =F80*D80 -> 50 | K80: =G80*D80 -> 50 | L80: =H80*D80 -> 0 | M80: =SUM(J80:L80) -> 100 | N80: =M80*(1+$N$96) -> 133.33333
A81: ='1. BRIEFING'!A88 -> 13.6 | B81: ='1. BRIEFING'!B88 -> INSTALAÇÃO DE CHUVEIRO | C81: ='1. BRIEFING'!C88 -> UN | D81: ='1. BRIEFING'!D88 -> 1 | E81: =I81 -> 100 | F81: 50 | G81: 50 | H81: 0 | I81: =SUM(F81:H81) -> 100 | J81: =F81*D81 -> 50 | K81: =G81*D81 -> 50 | L81: =H81*D81 -> 0 | M81: =SUM(J81:L81) -> 100 | N81: =M81*(1+$N$96) -> 133.33333
A82: ='1. BRIEFING'!A89 -> 14 | B82: ='1. BRIEFING'!B89 -> SERVIÇO EM PINTURA | J82: =SUM(J83:J88) -> 1080 | K82: =SUM(K83:K88) -> 0 | L82: =SUM(L83:L88) -> 0 | M82: =SUM(M83:M88) -> 1080 | N82: =SUM(N83:N88) -> 1440
A83: ='1. BRIEFING'!A90 -> 14.1 | B83: ='1. BRIEFING'!B90 -> APLICAÇÃO DE SELADOR ACRILICO PAREDE E FORRO | C83: ='1. BRIEFING'!C90 -> M2 | D83: ='1. BRIEFING'!D90 -> 1 | E83: =I83 -> 180 | F83: 180 | G83: 0 | H83: 0 | I83: =SUM(F83:H83) -> 180 | J83: =F83*D83 -> 180 | K83: =G83*D83 -> 0 | L83: =H83*D83 -> 0 | M83: =SUM(J83:L83) -> 180 | N83: =M83*(1+$N$96) -> 240
A84: ='1. BRIEFING'!A91 -> 14.2 | B84: ='1. BRIEFING'!B91 -> APLICAÇÃO E LIXAMENTO DE MASSA CORRIDA EM FORRO DE GESSO | C84: ='1. BRIEFING'!C91 -> M2 | D84: ='1. BRIEFING'!D91 -> 1 | E84: =I84 -> 180 | F84: 180 | G84: 0 | H84: 0 | I84: =SUM(F84:H84) -> 180 | J84: =F84*D84 -> 180 | K84: =G84*D84 -> 0 | L84: =H84*D84 -> 0 | M84: =SUM(J84:L84) -> 180 | N84: =M84*(1+$N$96) -> 240
A85: ='1. BRIEFING'!A92 -> 14.3 | B85: ='1. BRIEFING'!B92 -> APLICAÇÃO DE TINTA EM FORRO EM GESSO COM TINA ACRÍLLICA ACETINADO NA COR | C85: ='1. BRIEFING'!C92 -> M² | D85: ='1. BRIEFING'!D92 -> 1 | E85: =I85 -> 180 | F85: 180 | G85: 0 | H85: 0 | I85: =SUM(F85:H85) -> 180 | J85: =F85*D85 -> 180 | K85: =G85*D85 -> 0 | L85: =H85*D85 -> 0 | M85: =SUM(J85:L85) -> 180 | N85: =M85*(1+$N$96) -> 240
A86: ='1. BRIEFING'!A93 -> 14.4 | B86: ='1. BRIEFING'!B93 -> APLICAÇÃO E LIXAMENTO DE MASSA CORRIDA EM PAREDE | C86: ='1. BRIEFING'!C93 -> M² | D86: ='1. BRIEFING'!D93 -> 1 | E86: =I86 -> 180 | F86: 180 | G86: 0 | H86: 0 | I86: =SUM(F86:H86) -> 180 | J86: =F86*D86 -> 180 | K86: =G86*D86 -> 0 | L86: =H86*D86 -> 0 | M86: =SUM(J86:L86) -> 180 | N86: =M86*(1+$N$96) -> 240
A87: ='1. BRIEFING'!A94 -> 14.5 | B87: ='1. BRIEFING'!B94 -> APLICAÇÃO DE TINTA ACRÍLICA EM PAREDE , ACETINADO COR | C87: ='1. BRIEFING'!C94 -> M² | D87: ='1. BRIEFING'!D94 -> 1 | E87: =I87 -> 180 | F87: 180 | G87: 0 | H87: 0 | I87: =SUM(F87:H87) -> 180 | J87: =F87*D87 -> 180 | K87: =G87*D87 -> 0 | L87: =H87*D87 -> 0 | M87: =SUM(J87:L87) -> 180 | N87: =M87*(1+$N$96) -> 240
A88: ='1. BRIEFING'!A95 -> 14.6 | B88: ='1. BRIEFING'!B95 -> APLICAÇÃO DE FUNDO, MASSA E TINTA EM PORTA DE MADEIRA, ACETINADO NA COR | C88: ='1. BRIEFING'!C95 -> UND | D88: ='1. BRIEFING'!D95 -> 1 | E88: =I88 -> 180 | F88: 180 | G88: 0 | H88: 0 | I88: =SUM(F88:H88) -> 180 | J88: =F88*D88 -> 180 | K88: =G88*D88 -> 0 | L88: =H88*D88 -> 0 | M88: =SUM(J88:L88) -> 180 | N88: =M88*(1+$N$96) -> 240
A89: ='1. BRIEFING'!A96 -> 15 | B89: ='1. BRIEFING'!B96 -> LIMPEZA FINAL | J89: =SUM(J90:J91) -> 180 | K89: =SUM(K90:K91) -> 0 | L89: =SUM(L90:L91) -> 400 | M89: =SUM(M90:M91) -> 580 | N89: =SUM(N90:N91) -> 773.33333 | O89: =N89/$N$92 -> 0.020082936
A90: ='1. BRIEFING'!A97 -> 15.1 | B90: ='1. BRIEFING'!B97 -> LIMPEZA FINAL DA OBRA | C90: ='1. BRIEFING'!C97 -> VB | D90: ='1. BRIEFING'!D97 -> 1 | E90: =I90 -> 180 | F90: 180 | G90: 0 | H90: 0 | I90: =SUM(F90:H90) -> 180 | J90: =F90*D90 -> 180 | K90: =G90*D90 -> 0 | L90: =H90*D90 -> 0 | M90: =SUM(J90:L90) -> 180 | N90: =M90*(1+$N$96) -> 240
A91: ='1. BRIEFING'!A98 -> 15.3 | B91: ='1. BRIEFING'!B98 -> REMOÇÃO DE ENTULHOS GERADOS PELA OBRA POR CARRO PEQUENOS | C91: ='1. BRIEFING'!C98 -> UN | D91: ='1. BRIEFING'!D98 -> 1 | E91: =I91 -> 400 | F91: 0 | G91: 0 | H91: 400 | I91: =SUM(F91:H91) -> 400 | J91: =F91*D91 -> 0 | K91: =G91*D91 -> 0 | L91: =H91*D91 -> 400 | M91: =SUM(J91:L91) -> 400 | N91: =M91*(1+$N$96) -> 533.33333
I92: TOTAIS | J92: =SUM(J89,J82,J75,J68,J64,J59,J52,J47,J42,J38,J32,J26,J24,J14,J8) -> 4095 | K92: =SUM(K89,K82,K75,K68,K64,K59,K52,K47,K42,K38,K32,K26,K24,K14,K8) -> 1110.24 | L92: =SUM(L89,L82,L75,L68,L64,L59,L52,L47,L42,L38,L32,L26,L24,L14,L8) -> 23675 | M92: =SUM(M89,M82,M75,M68,M64,M59,M52,M47,M42,M38,M32,M26,M24,M14,M8) -> 28880.24 | N92: =SUM(N89,N82,N75,N68,N64,N59,N52,N47,N42,N38,N32,N26,N24,N14,N8) -> 38506.987
D94: PREÇO DE VENDA | L94: TOTAL CUSTO | M94: =M92 -> 28880.24 | N94: =N92 -> 38506.987
M96: BDI% | N96: ='0. P. VENDA'!C28 -> 0.33333333
M98: ADM CENTRAL | N98: 0.02
M99: CUSTOS INDIRETOS | N99: 0
M100: CUSTO FINANC. | N100: 0.01
M101: IMPOSTO | N101: 0.07
M102: LUCRO | N102: 0.15

Sheet 4. CUSTO IND
G1: Normalmente varia de 5% a 30% do custo total da obra
B2: EQUIPE TÉCNICA | G2: CUSTO INDIRETO | H2: =SUM(H3:H9,J3:J9) -> 0
B3: CARGOS | C3: QNTD | D3: SALÁRIO | E3: TOTAL | G3: EQUIPE TECNICA | H3: =E9 -> 0 | I3: EQP EPI | J3: =E91+J91 -> 0 | L3: O QUE INCLUI?
B4: ENGENHEIRO CIVIL (MÊS) | C4: 0 | D4: 0 | E4: =D4*C4 -> 0 | G4: EQUIPE DE SUPORTE | H4: =E20+J20 -> 0 | I4: FERRAMENTA | J4: =E116+J116 -> 0 | L4: CUSTOS ACRESCIDOS DOS ENCARGOS SOCIAIS E TRABALHISTAS (MENSALISTA)
B5: ENGENHEIRO CIVIL (VISITA) | C5: 0 | D5: 0 | E5: =D5*C5 -> 0 | G5: EQUIPE ADMINISTRATIVA | H5: =E29+J29 -> 0 | I5: DESP CORRENTE | J5: =E131 -> 0
B6: ENCARREGADO DE OBRAS | C6: 0 | D6: 0 | E6: =D6*C6 -> 0 | G6: MOBILIZAÇÃO E DESMOBILIZAÇÃO | H6: =E41 -> 0 | I6: DESP PESSOAL | J6: =E143 -> 0
B7: ENCARREGADO (SEMANA) | C7: 0 | D7: 0 | E7: =D7*C7 -> 0 | G7: EQP CANTEIRO | H7: =E59+J59 -> 0 | I7: SERV TERCEIRO | J7: =E153 -> 0
B8: ESTÁGIARIO/MÊS (BOLSA+PASSAG+REFEIÇÃO) | C8: 0 | D8: 0 | E8: =D8*C8 -> 0 | G8: EQP ADMINISTRATIVA | H8: =E73+J73 -> 0 | I8: TAXAS E EMOLU | J8: =E163 -> 0
D9: TOTAL EQP TÉCNICA | E9: =SUM(E4:E8) -> 0 | G9: EQP PROT. COLETIVA | H9: =E81 -> 0 | I9: DIVERSOS | J9: =E180 -> 0
B11: EQUIPE DE SUPORTE
B12: FUNÇÕES | C12: QNTD | D12: SALÁRIO | E12: TOTAL | G12: FUNÇÕES | H12: QNTD | I12: SALÁRIO | J12: TOTAL | L12: O QUE INCLUI?
B13: ALMOXARIFE | C13: 0 | D13: 0 | E13: =D13*C13 -> 0 | G13: TOPÓGRAFO | H13: 0 | I13: 0 | J13: =I13*H13 -> 0 | L13: CUSTOS ACRESCIDOS DOS ENCARGOS SOCIAIS E TRABALHISTAS (MENSALISTA)
B14: FERRAMENTEIRO | C14: 0 | D14: 0 | E14: =D14*C14 -> 0 | G14: AUXILIAR TOPOGAFIA (Hr) | H14: 0 | I14: 0 | J14: =I14*H14 -> 0
B15: APONTADOR | C15: 0 | D15: 0 | E15: =D15*C15 -> 0 | G15: OPERADORES DE EQP GERAIS | H15: 0 | I15: 0 | J15: =I15*H15 -> 0
B16: COMPRADOR | C16: 0 | D16: 0 | E16: =D16*C16 -> 0 | G16: MÉDICO | H16: 0 | I16: 0 | J16: =I16*H16 -> 0
B17: AUX. LABORATORISTA (Hr) | C17: 0 | D17: 0 | E17: =D17*C17 -> 0 | G17: ENFERMEIRO | H17: 0 | I17: 0 | J17: =I17*H17 -> 0
B18: AUX. SERVIÇOS GERAIS (ELE, ENCAN, SERV) Hr | C18: 0 | D18: 0 | E18: =D18*C18 -> 0 | G18: COZINHEIRO | H18: 0 | I18: 0 | J18: =I18*H18 -> 0
B19: ASSISTENCIA SOCIAL | C19: 0 | D19: 0 | E19: =D19*C19 -> 0 | G19: AUXILIAR DE COZINHA | H19: 0 | I19: 0 | J19: =I19*H19 -> 0
D20: TOTAL EQP | E20: =SUM(E13:E19) -> 0 | I20: TOTAL EQP | J20: =SUM(J13:J19) -> 0
B22: EQUIPE ADMINISTRATIVA
B23: FUNÇÕES | C23: QNTD | D23: SALÁRIO | E23: TOTAL | G23: FUNÇÕES | H23: QNTD | I23: SALÁRIO | J23: TOTAL
B24: CHEFE DE ESCRITORIO | C24: 0 | D24: 0 | E24: =D24*C24 -> 0 | G24: PORTEIRO | H24: 0 | I24: 0 | J24: =I24*H24 -> 0
B25: AUXILIAR ADMINISTRATIVO | C25: 0 | D25: 0 | E25: =D25*C25 -> 0 | G25: VIGIA NOTURNO | H25: 0 | I25: 0 | J25: =I25*H25 -> 0
B26: SECRETÁRIA | C26: 0 | D26: 0 | E26: =D26*C26 -> 0 | G26: - | H26: 0 | I26: 0 | J26: =I26*H26 -> 0
B27: FINANCEIRO | C27: 0 | D27: 0 | E27: =D27*C27 -> 0 | G27: - | H27: 0 | I27: 0 | J27: =I27*H27 -> 0
B28: FAXINEIRA | C28: 0 | D28: 0 | E28: =D28*C28 -> 0 | G28: - | H28: 0 | I28: 0 | J28: =I28*H28 -> 0
D29: TOTAL EQP | E29: =SUM(E24:E28) -> 0 | I29: TOTAL EQP | J29: =SUM(J24:J28) -> 0
B31: MOBILIZAÇÃO E DESMOBILIZAÇÃO
B32: DESCRIÇÃO | C32: QNTD | D32: R$ VALOR | E32: R$ TOTAL | G32: O QUE INCLUI?
B33: MOBILIZAÇÃO E DESMOBILIZAÇÃO DO CANTEIRO | C33: 0 | D33: 0 | E33: =D33*C33 -> 0 | G33: MONTAGEM E DESMONTAGEM DE CONSTRUÇÕES PROVISORIAS
B34: MOBILIZAÇÃO E DESMOBILIZAÇÃO DE PESSOAL (TRANSPORTES) | C34: 0 | D34: 0 | E34: =D34*C34 -> 0 | G34: CUSTO DE DESLOCAMENTO (PASSAGEM, TRANSPORTE) E ALOJAMENTO PROVISORIO
B35: MOBILIZAÇÃO E DESMOBILIZAÇÃO DE EQUIPAMENTOS | C35: 0 | D35: 0 | E35: =D35*C35 -> 0 | G35: TRANSPORTE EM CARRETAS, MONTAGEM DE GRUA
B36: ALUGUEL DE IMOVIES PARA ESCRITÓRIO, DEPÓSITO, CONTAINES, ETC. (Mês) | C36: 0 | D36: 0 | E36: =D36*C36 -> 0 | G36: CUSTO DE LOCAÇÃO
B37: TAPUMES E CERCAS | C37: 0 | D37: 0 | E37: =D37*C37 -> 0 | G37: CONSTRUÇÃO E REMOÇÃO AO FINAL DA OBRA
B38: ILUMINAÇÃO DE CAMPOS | C38: 0 | D38: 0 | E38: =D38*C38 -> 0 | G38: MONTAGEM E REMOÇÃO DAS ESTRUTURAS
B39: LIGAÇÕES PROVISÓRIAS DE AGUA, LUZ , ESGOTO, TELEFONE | C39: 0 | D39: 0 | E39: =D39*C39 -> 0 | G39: CUSTO DE MATERIAL, INSTALAÇÃO DE EQUIPAMENTO, TAXA DE LIGAÇÃO
B40: PLACAS DA OBRA (M²) | C40: 0 | D40: 0 | E40: =D40*C40 -> 0
D41: TOTAL MOB E DESMOB | E41: =SUM(E33:E40) -> 0
B43: EQUIPAMENTO DO CANTEIRO (SE NÃO EXISTIR NA CPU)
B44: DESCRIÇÃO | C44: QNTD | D44: R$ UNTI | E44: R$ TOTAL | G44: DESCRIÇÃO | H44: QNTD | I44: R$ UNTI | J44: R$ TOTAL | K44: O QUE INCLUI?
B45: ANDAIME (M/Mês - LOCAÇÃO) | C45: 1 | D45: 0 | E45: =D45*C45 -> 0 | G45: - | H45: 0 | I45: 0 | J45: =I45*H45 -> 0
B46: BALANCIM (Mês) | C46: 0 | D46: 0 | E46: =D46*C46 -> 0 | G46: - | H46: 0 | I46: 0 | J46: =I46*H46 -> 0 | K46: CUSTO DE PROPRIEDADE E OPERAÇÃO (SE PROPRIO) OU CUSTO POR MÊS DE LOCAÇÃO
B47: BETONEIRA (Mês) | C47: 0 | D47: 0 | E47: =D47*C47 -> 0 | G47: - | H47: 0 | I47: 0 | J47: =I47*H47 -> 0
B48: ESCORAS METÁLICAS (MêS) | C48: 0 | D48: 0 | E48: =D48*C48 -> 0 | G48: - | H48: 0 | I48: 0 | J48: =I48*H48 -> 0
B49: BOMBA HIDRAULICA | C49: 0 | D49: 0 | E49: =D49*C49 -> 0 | G49: - | H49: 0 | I49: 0 | J49: =I49*H49 -> 0
B50: MAÇARICO | C50: 0 | D50: 0 | E50: =D50*C50 -> 0 | G50: - | H50: 0 | I50: 0 | J50: =I50*H50 -> 0
B51: MAQUINA LAVA JATO | C51: 0 | D51: 0 | E51: =D51*C51 -> 0 | G51: - | H51: 0 | I51: 0 | J51: =I51*H51 -> 0
B52: MAQUINA DE SOLDA | C52: 0 | D52: 0 | E52: =D52*C52 -> 0 | G52: - | H52: 0 | I52: 0 | J52: =I52*H52 -> 0
B53: MARTELETE C/ PONTEIO | C53: 0 | D53: 0 | E53: =D53*C53 -> 0 | G53: - | H53: 0 | I53: 0 | J53: =I53*H53 -> 0
B54: FURADEIRA | C54: 0 | D54: 0 | E54: =D54*C54 -> 0 | G54: - | H54: 0 | I54: 0 | J54: =I54*H54 -> 0
B55: LIXADEIRA | C55: 0 | D55: 0 | E55: =D55*C55 -> 0 | G55: - | H55: 0 | I55: 0 | J55: =I55*H55 -> 0
B56: RETROESCAVAREIA | C56: 0 | D56: 0 | E56: =D56*C56 -> 0 | G56: - | H56: 0 | I56: 0 | J56: =I56*H56 -> 0
B57: SERRA CIRCULAR COM SERRA | C57: 0 | D57: 0 | E57: =D57*C57 -> 0 | G57: - | H57: 0 | I57: 0 | J57: =I57*H57 -> 0
B58: VIBRADOR DE IMERSÃO (MOTOR E MANGOTE) | C58: 0 | D58: 0 | E58: =D58*C58 -> 0 | G58: - | H58: 0 | I58: 0 | J58: =I58*H58 -> 0
D59: TOTAL EQP CANTEIRO | E59: =SUM(E45:E58) -> 0 | I59: TOTAL EQP CANTEIRO | J59: =SUM(J45:J58) -> 0
B61: EQUIPAMENTOS ADMINISTRATIVOS (ESCRITÓRIO DE CAMPO)
B62: DESCRIÇÃO | C62: QNTD | D62: R$ UNTI | E62: R$ TOTAL | G62: DESCRIÇÃO | H62: QNTD | I62: R$ UNTI | J62: R$ TOTAL | K62: O QUE INCLUI?
B63: AR CONDICIONADO | C63: 0 | D63: 0 | E63: =D63*C63 -> 0 | G63: SANITÁRIOS PORTAVEIS | H63: 0 | I63: 0 | J63: =I63*H63 -> 0 | K63: CUSTO DE PROPRIEDADE OU LOCAÇÃO
B64: BEBEDOR | C64: 0 | D64: 0 | E64: =D64*C64 -> 0 | G64: SIRENE | H64: 0 | I64: 0 | J64: =I64*H64 -> 0
B65: CAFETEIRA | C65: 0 | D65: 0 | E65: =D65*C65 -> 0 | G65: TELEVISÃO | H65: 0 | I65: 0 | J65: =I65*H65 -> 0
B66: SISTEMA DE CAMERAS | C66: 0 | D66: 0 | E66: =D66*C66 -> 0 | H66: 0 | I66: 0 | J66: =I66*H66 -> 0
B67: INTERNET CABEADA/WIFI | C67: 0 | D67: 0 | E67: =D67*C67 -> 0 | H67: 0 | I67: 0 | J67: =I67*H67 -> 0
B68: NOTBOOKS | C68: 0 | D68: 0 | E68: =D68*C68 -> 0 | H68: 0 | I68: 0 | J68: =I68*H68 -> 0
B69: IMPRESSORA | C69: 0 | D69: 0 | E69: =D69*C69 -> 0 | H69: 0 | I69: 0 | J69: =I69*H69 -> 0
B70: MICROONDAS | C70: 0 | D70: 0 | E70: =D70*C70 -> 0 | H70: 0 | I70: 0 | J70: =I70*H70 -> 0
B71: MOBILIARIO (MESA/CADEIRA/ESTANTES/ARMARIOS) | C71: 0 | D71: 0 | E71: =D71*C71 -> 0 | H71: 0 | I71: 0 | J71: =I71*H71 -> 0
B72: RELÓGIO DE PONTO | C72: 0 | D72: 0 | E72: =D72*C72 -> 0 | I72: 0 | J72: =I72*H72 -> 0
D73: TOTAL EQP ADM | E73: =SUM(E63:E72) -> 0 | I73: TOTAL EQP ADM | J73: =SUM(J63:J72) -> 0
B75: EQUIPAMENTO DE PROTEÇÃO COLETIVA (SE NÃO ESTIVER INCLUIDO NOS ENCARGOS SOCIAIS)
B76: DESCRIÇÃO | C76: QNTD | D76: R$ UNTI | E76: R$ TOTAL
B77: BANDEIJA DE PROTEÇÃO (COM PERFIS) | C77: 0 | D77: 0 | E77: =D77*C77 -> 0
B78: EXTINTOR DE INCENDIO | C78: 0 | D78: 0 | E78: =D78*C78 -> 0
B79: SINALIZAÇÃO (FAIXA, PLACAS, CONES, CAVALETES) | C79: 0 | D79: 0 | E79: =D79*C79 -> 0
B80: TELA DE PROTEÇÃO (M²) | C80: 0 | D80: 0 | E80: =D80*C80 -> 0
D81: TOTAL EQP PROT. COLETIVA | E81: =SUM(E77:E80) -> 0
B83: EQUIPAMENTO DE PROTEÇÃO INDIVIDUAL (EPI - SE NÃO ESTIVER INCLUIDO NOS ENCARGOS SOCIAIS)
B84: DESCRIÇÃO | C84: QNTD | D84: R$ UNTI | E84: R$ TOTAL | G84: DESCRIÇÃO | H84: QNTD | I84: R$ UNTI | J84: R$ TOTAL | K84: O QUE INCLUI?
B85: AVENTAL DE SEGURANÇA DE RASPA DE COURO | D85: 0 | E85: =D85*C85 -> 0 | G85: CORDA 12 MM (M) | H85: 0 | I85: 0 | J85: =I85*H85 -> 0 | K85: CUSTO DE AQUISIÇÃO OU VERBA
B86: BOTA DE PVC PRETA, CANO MÉDIO | C86: 0 | D86: 0 | E86: =D86*C86 -> 0 | G86: FARDAMENTO | H86: 0 | I86: 0 | J86: =I86*H86 -> 0
B87: CABO DE SUSTENTAÇÃO | D87: 0 | E87: =D87*C87 -> 0 | G87: LUVA | H87: 0 | I87: 0 | J87: =I87*H87 -> 0
B88: CAPA DE CHUVA | D88: 0 | E88: =D88*C88 -> 0 | G88: ÓCULOS | H88: 0 | I88: 0 | J88: =I88*H88 -> 0
B89: CAPACETE DE SEGURANÇA | C89: 0 | D89: 0 | E89: =D89*C89 -> 0 | G89: PROTETOR AURICULAR | H89: 0 | I89: 0 | J89: =I89*H89 -> 0
B90: CINTO COM TALABARTE (LOCAÇÃO) | C90: 0 | D90: 0 | E90: =D90*C90 -> 0 | G90: PROTETOR FACIAL | H90: 0 | I90: 0 | J90: =I90*H90 -> 0
D91: TOTAL EQP EPI | E91: =SUM(E85:E90) -> 0 | I91: TOTAL EQP EPI | J91: =SUM(J85:J90) -> 0
B93: FERRAMENTAS (SE NÃO ESTIVER INCLUIDO NOS ENCARGOS SOCIAIS)
B94: DESCRIÇÃO | C94: QNTD | D94: R$ UNTI | E94: R$ TOTAL | G94: DESCRIÇÃO | H94: QNTD | I94: R$ UNTI | J94: R$ TOTAL | K94: O QUE INCLUI?
B95: ARCO DE SERRA | C95: 0 | D95: 0 | E95: =D95*C95 -> 0 | G95: MARRETA | H95: 2 | I95: 0 | J95: =I95*H95 -> 0 | K95: CUSTO DE AQUISIÇÃO OU VERBA
B96: BALDE PLASTICO CAP 10 L | C96: 2 | D96: 0 | E96: =D96*C96 -> 0 | G96: MARTELO | H96: 0 | I96: 0 | J96: =I96*H96 -> 0
B97: BROCA | C97: 0 | D97: 0 | E97: =D97*C97 -> 0 | G97: MASSAIRA | H97: 0 | I97: 0 | J97: =I97*H97 -> 0
B98: CARRINHO DE MÃO DE AÇO CAP 50 À 60 L | C98: 0 | D98: 0 | E98: =D98*C98 -> 0 | G98: METRO DE MADEIRA | H98: 0 | I98: 0 | J98: =I98*H98 -> 0
B99: CAVADEIRA | C99: 0 | D99: 0 | E99: =D99*C99 -> 0 | G99: PÁ COM CABO | H99: 0 | I99: 0 | J99: =I99*H99 -> 0
B100: CHAVE DE DOBRAR FERRO | C100: 0 | D100: 0 | E100: =D100*C100 -> 0 | G100: PENEIRA | H100: 0 | I100: 0 | J100: =I100*H100 -> 0
B101: COLHER DE PEDREIRO FORJADA 8" CANTO REDONDO | C101: 0 | D101: 0 | E101: =D101*C101 -> 0 | G101: PICARETA COM CABO | H101: 0 | I101: 0 | J101: =I101*H101 -> 0
B102: CORDA | C102: 0 | D102: 0 | E102: =D102*C102 -> 0 | G102: PONTEIRO DE AÇO | H102: 0 | I102: 0 | J102: =I102*H102 -> 0
B103: DESEMPENADEIRA DE AÇO LISA 12 x *25* | C103: 0 | D103: 0 | E103: =D103*C103 -> 0 | G103: PRUMO | H103: 0 | I103: 0 | J103: =I103*H103 -> 0
B104: ENXADA COM CABO | C104: 0 | D104: 0 | E104: =D104*C104 -> 0 | G104: RÉGUA DE ALUMINIO (M) | H104: 0 | I104: 0 | J104: =I104*H104 -> 0
B105: ESCANTILHÃO | C105: 0 | D105: 0 | E105: =D105*C105 -> 0 | G105: RONDANA (MOITÃO) | H105: 0 | I105: 0 | J105: =I105*H105 -> 0
B106: ESCOVA DE AÇO | C106: 0 | D106: 0 | E106: =D106*C106 -> 0 | G106: ROLO PARA PINTURA | H106: 0 | I106: 0 | J106: =I106*H106 -> 0
B107: FITA ISOLANTE | C107: 0 | D107: 0 | E107: =D107*C107 -> 0 | G107: SERRA RÁPIDA | H107: 0 | I107: 0 | J107: =I107*H107 -> 0
... B114: MAÇARICO | C114: 0 | D114: 0 | E114: =D114*C114 -> 0 | G114: TRINCHA | H114: 0 | I114: 0 | J114: =I114*H114 -> 0
...

Sheet DIM EQP
B2: QUADRO DE DURAÇÃO DAS ATIVIDADES E RECURSOS
B3: DESCRIÇÃO DO SERVIÇO | C3: UNID. | D3: QTDE | E3: EQUIPE BÁSICA | M3: ÍNDICE DA EQUIPE | O3: JORNADA (h/dia) | P3: DIAS DA EQUIPE BÁSICA | Q3: DURAÇÃO ADOTADA (dias) | R3: QTDE DE EQUIPES | S3: RECURSOS
E4: PED | F4: CARP | G4: ARM | H4: ELET | I4: ENCA | J4: PINT | K4: AJUD | L4: SER | S4: PED | T4: CARP | U4: ARM | V4: ELET | W4: ENCA | X4: PINT | Y4: AJUD | Z4: SER
B5: ='1. BRIEFING'!B14 -> DEMOLIÇÃO E RETIRADA
B6: ='1. BRIEFING'!B15 -> DEMOLIÇÃO DE ALVENARIA DE VEDAÇÃO | C6: ='1. BRIEFING'!C15 -> M² | D6: 100 | L6: 4 | M6: =2.33/L6 -> 0.5825 | N6: h/m³ | O6: 8 | P6: =ROUNDUP(AA6,0) -> 8 | Q6: 0 | R6: =P6/Q6 -> #DIV/0! | S6: =E6*$R6 -> #DIV/0! | T6: =F6*$R6 -> #DIV/0! | U6: =G6*$R6 -> #DIV/0! | V6: =H6*$R6 -> #DIV/0! | W6: =I6*$R6 -> #DIV/0! | X6: =J6*$R6 -> #DIV/0! | Y6: =K6*$R6 -> #DIV/0! | Z6: =L6*$R6 -> #DIV/0! | AA6: =D6/(O6/M6) -> 7.28125
B7: ='1. BRIEFING'!B16 -> REMOÇÃO DE BANCADAS EM GRANITO | C7: ='1. BRIEFING'!C16 -> UND | D7: ='1. BRIEFING'!D16 -> 1,00 | L7: 1 | M7: 0.5 | N7: h/und | O7: 8 | P7: =ROUNDUP(AA7,0) -> 1 | R7: =P7/Q7 -> #DIV/0! | S7: =E7*$R7 -> #DIV/0! | T7: =F7*$R7 -> #DIV/0! | U7: =G7*$R7 -> #DIV/0! | V7: =H7*$R7 -> #DIV/0! | W7: =I7*$R7 -> #DIV/0! | X7: =J7*$R7 -> #DIV/0! | Y7: =K7*$R7 -> #DIV/0! | Z7: =L7*$R7 -> #DIV/0! | AA7: =D7/(O7/M7) -> 0.0625
B8: ='1. BRIEFING'!B17 -> REMOÇÃO DE LOUÇAS E METAIS | C8: ='1. BRIEFING'!C17 -> VB | D8: ='1. BRIEFING'!D17 -> 1,00 | L8: 1 | M8: 0.2 | N8: h/und | O8: 8 | P8: =ROUNDUP(AA8,0) -> 1 | R8: =P8/Q8 -> #DIV/0! | S8: =E8*$R8 -> #DIV/0! | T8: =F8*$R8 -> #DIV/0! | U8: =G8*$R8 -> #DIV/0! | V8: =H8*$R8 -> #DIV/0! | W8: =I8*$R8 -> #DIV/0! | X8: =J8*$R8 -> #DIV/0! | Y8: =K8*$R8 -> #DIV/0! | Z8: =L8*$R8 -> #DIV/0! | AA8: =D8/(O8/M8) -> 0.025
B9: ='1. BRIEFING'!B18 -> REMOÇÃO DE PORTAS INTERNAS EM MADEIRA | C9: ='1. BRIEFING'!C18 -> UN | D9: ='1. BRIEFING'!D18 -> 1,00 | L9: 1 | M9: 0.2 | N9: h/und | O9: 8 | P9: =ROUNDUP(AA9,0) -> 1 | R9: =P9/Q9 -> #DIV/0! | S9: =E9*$R9 -> #DIV/0! | T9: =F9*$R9 -> #DIV/0! | U9: =G9*$R9 -> #DIV/0! | V9: =H9*$R9 -> #DIV/0! | W9: =I9*$R9 -> #DIV/0! | X9: =J9*$R9 -> #DIV/0! | Y9: =K9*$R9 -> #DIV/0! | Z9: =L9*$R9 -> #DIV/0! | AA9: =D9/(O9/M9) -> 0.025
B10: ='1. BRIEFING'!B19 -> DEMOLIÇÃO DE REVESTIMENTO CERÂMICO EM PAREDE | C10: ='1. BRIEFING'!C19 -> M² | D10: ='1. BRIEFING'!D19 -> 1,00 | L10: 1 | M10: 0.72 | N10: h/m² | O10: 8 | P10: =ROUNDUP(AA10,0) -> 1 | R10: =P10/Q10 -> #DIV/0! | S10: =E10*$R10 -> #DIV/0! | T10: =F10*$R10 -> #DIV/0! | U10: =G10*$R10 -> #DIV/0! | V10: =H10*$R10 -> #DIV/0! | W10: =I10*$R10 -> #DIV/0! | X10: =J10*$R10 -> #DIV/0! | Y10: =K10*$R10 -> #DIV/0! | Z10: =L10*$R10 -> #DIV/0! | AA10: =D10/(O10/M10) -> 0.09
B11: ='1. BRIEFING'!B20 -> DEMOLIÇÃO DE REVESTIMENTO CERÂMICO EM PISO | C11: ='1. BRIEFING'!C20 -> M² | D11: ='1. BRIEFING'!D20 -> 1,00 | L11: 1 | M11: 0.72 | N11: h/m² | O11: 8 | P11: =ROUNDUP(AA11,0) -> 1 | R11: =P11/Q11 -> #DIV/0! | S11: =E11*$R11 -> #DIV/0! | T11: =F11*$R11 -> #DIV/0! | U11: =G11*$R11 -> #DIV/0! | V11: =H11*$R11 -> #DIV/0! | W11: =I11*$R11 -> #DIV/0! | X11: =J11*$R11 -> #DIV/0! | Y11: =K11*$R11 -> #DIV/0! | Z11: =L11*$R11 -> #DIV/0! | AA11: =D11/(O11/M11) -> 0.09
B12: ='1. BRIEFING'!B21 -> DEMOLIÇÃO DE FORRO EM GESSO/PVC | C12: ='1. BRIEFING'!C21 -> M² | D12: ='1. BRIEFING'!D21 -> 1,00 | L12: 1 | M12: 0.14 | N12: h/m² | O12: 8 | P12: =ROUNDUP(AA12,0) -> 1 | R12: =P12/Q12 -> #DIV/0! | S12: =E12*$R12 -> #DIV/0! | T12: =F12*$R12 -> #DIV/0! | U12: =G12*$R12 -> #DIV/0! | V12: =H12*$R12 -> #DIV/0! | W12: =I12*$R12 -> #DIV/0! | X12: =J12*$R12 -> #DIV/0! | Y12: =K12*$R12 -> #DIV/0! | Z12: =L12*$R12 -> #DIV/0! | AA12: =D12/(O12/M12) -> 0.0175
B13: ='1. BRIEFING'!B22 -> REMOÇÃO DE LUMINÁRIAS INTERNAS (FORRO) | C13: ='1. BRIEFING'!C22 -> UN | D13: ='1. BRIEFING'!D22 -> 1,00 | L13: 1 | M13: 0.1 | N13: h/und | O13: 8 | P13: =ROUNDUP(AA13,0) -> 1 | R13: =P13/Q13 -> #DIV/0! | S13: =E13*$R13 -> #DIV/0! | T13: =F13*$R13 -> #DIV/0! | U13: =G13*$R13 -> #DIV/0! | V13: =H13*$R13 -> #DIV/0! | W13: =I13*$R13 -> #DIV/0! | X13: =J13*$R13 -> #DIV/0! | Y13: =K13*$R13 -> #DIV/0! | Z13: =L13*$R13 -> #DIV/0! | AA13: =D13/(O13/M13) -> 0.0125
B14: ='1. BRIEFING'!B23 -> REMOÇÃO DOS ENTULHOS POR SACOS E CARRO PEQUENO | C14: ='1. BRIEFING'!C23 -> UN | D14: ='1. BRIEFING'!D23 -> 1,00 | L14: 1 | M14: 0.5 | N14: h/m³ | O14: 8 | P14: =ROUNDUP(AA14,0) -> 1 | R14: =P14/Q14 -> #DIV/0! | S14: =E14*$R14 -> #DIV/0! | T14: =F14*$R14 -> #DIV/0! | U14: =G14*$R14 -> #DIV/0! | V14: =H14*$R14 -> #DIV/0! | W14: =I14*$R14 -> #DIV/0! | X14: =J14*$R14 -> #DIV/0! | Y14: =K14*$R14 -> #DIV/0! | Z14: =L14*$R14 -> #DIV/0! | AA14: =D14/(O14/M14) -> 0.0625
B15: ='1. BRIEFING'!B24 -> SERVIÇO EM ALVENARIA | AA15: =D15/(O15/M15) -> #DIV/0!
B16: ='1. BRIEFING'!B25 -> ASSENTAMENTO DE ALVENARIA DE VEDAÇÃO | C16: ='1. BRIEFING'!C25 -> M² | D16: ='1. BRIEFING'!D25 -> 1 | E16: 1 | L16: 1 | M16: 1.61 | N16: h/m² | O16: 8 | P16: =ROUNDUP(AA16,0) -> 1 | R16: =P16/Q16 -> #DIV/0! | S16: =E16*$R16 -> #DIV/0! | T16: =F16*$R16 -> #DIV/0! | U16: =G16*$R16 -> #DIV/0! | V16: =H16*$R16 -> #DIV/0! | W16: =I16*$R16 -> #DIV/0! | X16: =J16*$R16 -> #DIV/0! | Y16: =K16*$R16 -> #DIV/0! | Z16: =L16*$R16 -> #DIV/0! | AA16: =D16/(O16/M16) -> 0.20125
B17: ='1. BRIEFING'!B29 -> INSTALAÇÃO HIDRÁULICA | AA17: =D17/(O17/M17) -> #DIV/0!
B18: ='1. BRIEFING'!B30 -> INSTALAÇAO DE PONTO DE ÁGUA FRIA | C18: ='1. BRIEFING'!C30 -> UN | D18: ='1. BRIEFING'!D30 -> 10 | M18: 1 | N18: h/und | O18: 8 | P18: =ROUNDUP(AA18,0) -> 2 | R18: =P18/Q18 -> #DIV/0! | S18: =E18*$R18 -> #DIV/0! | T18: =F18*$R18 -> #DIV/0! | U18: =G18*$R18 -> #DIV/0! | V18: =H18*$R18 -> #DIV/0! | W18: =I18*$R18 -> #DIV/0! | X18: =J18*$R18 -> #DIV/0! | Y18: =K18*$R18 -> #DIV/0! | Z18: =L18*$R18 -> #DIV/0! | AA18: =D18/(O18/M18) -> 1.25
B19: ='1. BRIEFING'!B31 -> INSTALAÇÃO DE PONTO DE ESGOTO 50 MM | C19: ='1. BRIEFING'!C31 -> UN | D19: ='1. BRIEFING'!D31 -> 1 | M19: 1 | N19: h/und | O19: 8 | P19: =ROUNDUP(AA19,0) -> 1 | R19: =P19/Q19 -> #DIV/0! | S19: =E19*$R19 -> #DIV/0! | T19: =F19*$R19 -> #DIV/0! | U19: =G19*$R19 -> #DIV/0! | V19: =H19*$R19 -> #DIV/0! | W19: =I19*$R19 -> #DIV/0! | X19: =J19*$R19 -> #DIV/0! | Y19: =K19*$R19 -> #DIV/0! | Z19: =L19*$R19 -> #DIV/0! | AA19: =D19/(O19/M19) -> 0.125
B20: ='1. BRIEFING'!B32 -> RELOCAÇÃO DE PONTO DE ESGOTO 100 MM | C20: ='1. BRIEFING'!C32 -> UN | D20: ='1. BRIEFING'!D32 -> 1 | M20: 1 | N20: h/und | O20: 8 | P20: =ROUNDUP(AA20,0) -> 1 | R20: =P20/Q20 -> #DIV/0! | S20: =E20*$R20 -> #DIV/0! | T20: =F20*$R20 -> #DIV/0! | U20: =G20*$R20 -> #DIV/0! | V20: =H20*$R20 -> #DIV/0! | W20: =I20*$R20 -> #DIV/0! | X20: =J20*$R20 -> #DIV/0! | Y20: =K20*$R20 -> #DIV/0! | Z20: =L20*$R20 -> #DIV/0! | AA20: =D20/(O20/M20) -> 0.125
B21: ='1. BRIEFING'!B33 -> INSTALAÇÃO DE PONTO DE REGISTRO DE GAVETA | C21: ='1. BRIEFING'!C33 -> UN | D21: ='1. BRIEFING'!D33 -> 1 | M21: 1 | N21: h/und | O21: 8 | P21: =ROUNDUP(AA21,0) -> 1 | R21: =P21/Q21 -> #DIV/0! | S21: =E21*$R21 -> #DIV/0! | T21: =F21*$R21 -> #DIV/0! | U21: =G21*$R21 -> #DIV/0! | V21: =H21*$R21 -> #DIV/0! | W21: =I21*$R21 -> #DIV/0! | X21: =J21*$R21 -> #DIV/0! | Y21: =K21*$R21 -> #DIV/0! | Z21: =L21*$R21 -> #DIV/0! | AA21: =D21/(O21/M21) -> 0.125
B22: ='1. BRIEFING'!B34 -> INSTALAÇÃO DE PONTO DE REGISTRO DE PRESSÃO | C22: ='1. BRIEFING'!C34 -> UN | D22: ='1. BRIEFING'!D34 -> 1 | M22: 1 | N22: h/und | O22: 8 | P22: =ROUNDUP(AA22,0) -> 1 | R22: =P22/Q22 -> #DIV/0! | S22: =E22*$R22 -> #DIV/0! | T22: =F22*$R22 -> #DIV/0! | U22: =G22*$R22 -> #DIV/0! | V22: =H22*$R22 -> #DIV/0! | W22: =I22*$R22 -> #DIV/0! | X22: =J22*$R22 -> #DIV/0! | Y22: =K22*$R22 -> #DIV/0! | Z22: =L22*$R22 -> #DIV/0! | AA22: =D22/(O22/M22) -> 0.125
B23: ='1. BRIEFING'!B35 -> INSTALAÇÃO ELÉTRICA | AA23: =D23/(O23/M23) -> #DIV/0!
B24: ='1. BRIEFING'!B36 -> INSTALAÇÃO DE INFRAESTRUTURA PARA TOMADA E ILUMINAÇÃO | C24: ='1. BRIEFING'!C36 -> UN | D24: ='1. BRIEFING'!D36 -> 1 | M24: 0.2 | N24: h/und | O24: 8 | P24: =ROUNDUP(AA24,0) -> 1 | R24: =P24/Q24 -> #DIV/0! | S24: =E24*$R24 -> #DIV/0! | T24: =F24*$R24 -> #DIV/0! | U24: =G24*$R24 -> #DIV/0! | V24: =H24*$R24 -> #DIV/0! | W24: =I24*$R24 -> #DIV/0! | X24: =J24*$R24 -> #DIV/0! | Y24: =K24*$R24 -> #DIV/0! | Z24: =L24*$R24 -> #DIV/0! | AA24: =D24/(O24/M24) -> 0.025
B25: ='1. BRIEFING'!B37 -> INSTALAÇÃO DE CABEAMENTO PARA PONTOS DE TOMADAS | C25: ='1. BRIEFING'!C37 -> UN | D25: ='1. BRIEFING'!D37 -> 1 | M25: 0.2 | N25: h/und | O25: 8 | P25: =ROUNDUP(AA25,0) -> 1 | R25: =P25/Q25 -> #DIV/0! | S25: =E25*$R25 -> #DIV/0! | T25: =F25*$R25 -> #DIV/0! | U25: =G25*$R25 -> #DIV/0! | V25: =H25*$R25 -> #DIV/0! | W25: =I25*$R25 -> #DIV/0! | X25: =J25*$R25 -> #DIV/0! | Y25: =K25*$R25 -> #DIV/0! | Z25: =L25*$R25 -> #DIV/0! | AA25: =D25/(O25/M25) -> 0.025
B26: ='1. BRIEFING'!B38 -> INSTALAÇÃO DE CABEAMENTO PARA PONTOS DE ILUMINAÇÃO | C26: ='1. BRIEFING'!C38 -> UN | D26: ='1. BRIEFING'!D38 -> 1 | M26: 0.2 | N26: h/und | O26: 8 | P26: =ROUNDUP(AA26,0) -> 1 | R26: =P26/Q26 -> #DIV/0! | S26: =E26*$R26 -> #DIV/0! | T26: =F26*$R26 -> #DIV/0! | U26: =G26*$R26 -> #DIV/0! | V26: =H26*$R26 -> #DIV/0! | W26: =I26*$R26 -> #DIV/0! | X26: =J26*$R26 -> #DIV/0! | Y26: =K26*$R26 -> #DIV/0! | Z26: =L26*$R26 -> #DIV/0! | AA26: =D26/(O26/M26) -> 0.025
B27: ='1. BRIEFING'!B39 -> REISNTALAÇÃO DE QUADRO DE DISTRIBUIÇÃO (ADEQUAÇÃO) | C27: ='1. BRIEFING'!C39 -> VB | D27: ='1. BRIEFING'!D39 -> 1 | M27: 0.2 | N27: h/und | O27: 8 | P27: =ROUNDUP(AA27,0) -> 1 | R27: =P27/Q27 -> #DIV/0! | S27: =E27*$R27 -> #DIV/0! | T27: =F27*$R27 -> #DIV/0! | U27: =G27*$R27 -> #DIV/0! | V27: =H27*$R27 -> #DIV/0! | W27: =I27*$R27 -> #DIV/0! | X27: =J27*$R27 -> #DIV/0! | Y27: =K27*$R27 -> #DIV/0! | Z27: =L27*$R27 -> #DIV/0! | AA27: =D27/(O27/M27) -> 0.025
B28: ='1. BRIEFING'!B40 -> INSTALAÇÃO DE INFRAESTRUTURA PARA PONTOS DE REDE/ANTENA/CAMERA/SOM | C28: ='1. BRIEFING'!C40 -> UN | D28: ='1. BRIEFING'!D40 -> 1 | M28: 0.2 | N28: h/und | O28: 8 | P28: =ROUNDUP(AA28,0) -> 1 | R28: =P28/Q28 -> #DIV/0! | S28: =E28*$R28 -> #DIV/0! | T28: =F28*$R28 -> #DIV/0! | U28: =G28*$R28 -> #DIV/0! | V28: =H28*$R28 -> #DIV/0! | W28: =I28*$R28 -> #DIV/0! | X28: =J28*$R28 -> #DIV/0! | Y28: =K28*$R28 -> #DIV/0! | Z28: =L28*$R28 -> #DIV/0! | AA28: =D28/(O28/M28) -> 0.025
B29: ='1. BRIEFING'!B41 -> INSTALAÇÃO DE EQUIPAMENTOS | AA29: =D29/(O29/M29) -> #DIV/0!
B30: ='1. BRIEFING'!B42 -> INSTALAÇÃO DE INFRA PARA AR CONDICIONADO | C30: ='1. BRIEFING'!C39 -> VB | D30: ='1. BRIEFING'!D39 -> 1 | N30: h/und | O30: 8 | P30: =ROUNDUP(AA30,0) -> #DIV/0! | R30: =P30/Q30 -> #DIV/0! | S30: =E30*$R30 -> #DIV/0! | T30: =F30*$R30 -> #DIV/0! | U30: =G30*$R30 -> #DIV/0! | V30: =H30*$R30 -> #DIV/0! | W30: =I30*$R30 -> #DIV/0! | X30: =J30*$R30 -> #DIV/0! | Y30: =K30*$R30 -> #DIV/0! | Z30: =L30*$R30 -> #DIV/0! | AA30: =D30/(O30/M30) -> #DIV/0!
B31: ='1. BRIEFING'!B43 -> INSTALAÇÃO DE BOILER | C31: ='1. BRIEFING'!C40 -> UN | D31: ='1. BRIEFING'!D40 -> 1 | N31: h/und | O31: 8 | P31: =ROUNDUP(AA31,0) -> #DIV/0! | R31: =P31/Q31 -> #DIV/0! | S31: =E31*$R31 -> #DIV/0! | T31: =F31*$R31 -> #DIV/0! | U31: =G31*$R31 -> #DIV/0! | V31: =H31*$R31 -> #DIV/0! | W31: =I31*$R31 -> #DIV/0! | X31: =J31*$R31 -> #DIV/0! | Y31: =K31*$R31 -> #DIV/0! | Z31: =L31*$R31 -> #DIV/0! | AA31: =D31/(O31/M31) -> #DIV/0!
B32: ='1. BRIEFING'!B44 -> INSTALAÇÃO DE EXAUSTOR l BWC CAMARIM E MAS | C32: ='1. BRIEFING'!C41 -> 0 | D32: ='1. BRIEFING'!D41 -> 0 | N32: h/und | O32: 8 | P32: =ROUNDUP(AA32,0) -> #DIV/0! | R32: =P32/Q32 -> #DIV/0! | S32: =E32*$R32 -> #DIV/0! | T32: =F32*$R32 -> #DIV/0! | U32: =G32*$R32 -> #DIV/0! | V32: =H32*$R32 -> #DIV/0! | W32: =I32*$R32 -> #DIV/0! | X32: =J32*$R32 -> #DIV/0! | Y32: =K32*$R32 -> #DIV/0! | Z32: =L32*$R32 -> #DIV/0! | AA32: =D32/(O32/M32) -> #DIV/0!
B33: ='1. BRIEFING'!B45 -> INSTALAÇÃO DE ILUMINAÇÃO | AA33: =D33/(O33/M33) -> #DIV/0!
B34: ='1. BRIEFING'!B46 -> INSTALAÇÃO DE LUMINÁRIA DE EMBUTIR QUADRADA 20W EM FORRO DE GESSO | C34: ='1. BRIEFING'!C43 -> UN | D34: ='1. BRIEFING'!D43 -> 1 | O34: 8 | P34: =ROUNDUP(AA34,0) -> #DIV/0! | R34: =P34/Q34 -> #DIV/0! | S34: =E34*$R34 -> #DIV/0! | T34: =F34*$R34 -> #DIV/0! | U34: =G34*$R34 -> #DIV/0! | V34: =H34*$R34 -> #DIV/0! | W34: =I34*$R34 -> #DIV/0! | X34: =J34*$R34 -> #DIV/0! | Y34: =K34*$R34 -> #DIV/0! | Z34: =L34*$R34 -> #DIV/0! | AA34: =D34/(O34/M34) -> #DIV/0!
B35: ='1. BRIEFING'!B47 -> INSTALAÇÃO DE DICROICAS DIRECIONAIS | C35: ='1. BRIEFING'!C44 -> UN | D35: ='1. BRIEFING'!D44 -> 1 | O35: 8 | P35: =ROUNDUP(AA35,0) -> #DIV/0! | R35: =P35/Q35 -> #DIV/0! | S35: =E35*$R35 -> #DIV/0! | T35: =F35*$R35 -> #DIV/0! | U35: =G35*$R35 -> #DIV/0! | V35: =H35*$R35 -> #DIV/0! | W35: =I35*$R35 -> #DIV/0! | X35: =J35*$R35 -> #DIV/0! | Y35: =K35*$R35 -> #DIV/0! | Z35: =L35*$R35 -> #DIV/0! | AA35: =D35/(O35/M35) -> #DIV/0!
B36: ='1. BRIEFING'!B48 -> INSTALAÇÃO DE FITA EM LED | C36: ='1. BRIEFING'!C45 -> 0 | D36: ='1. BRIEFING'!D45 -> 0 | O36: 8 | P36: =ROUNDUP(AA36,0) -> #DIV/0! | R36: =P36/Q36 -> #DIV/0! | S36: =E36*$R36 -> #DIV/0! | T36: =F36*$R36 -> #DIV/0! | U36: =G36*$R36 -> #DIV/0! | V36: =H36*$R36 -> #DIV/0! | W36: =I36*$R36 -> #DIV/0! | X36: =J36*$R36 -> #DIV/0! | Y36: =K36*$R36 -> #DIV/0! | Z36: =L36*$R36 -> #DIV/0! | AA36: =D36/(O36/M36) -> #DIV/0!
B37: ='1. BRIEFING'!B49 -> INSTALAÇÃO DE PENDENTE | C37: ='1. BRIEFING'!C46 -> UN | D37: ='1. BRIEFING'!D46 -> 1 | O37: 8 | P37: =ROUNDUP(AA37,0) -> #DIV/0! | R37: =P37/Q37 -> #DIV/0! | S37: =E37*$R37 -> #DIV/0! | T37: =F37*$R37 -> #DIV/0! | U37: =G37*$R37 -> #DIV/0! | V37: =H37*$R37 -> #DIV/0! | W37: =I37*$R37 -> #DIV/0! | X37: =J37*$R37 -> #DIV/0! | Y37: =K37*$R37 -> #DIV/0! | Z37: =L37*$R37 -> #DIV/0! | AA37: =D37/(O37/M37) -> #DIV/0!
B38: ='1. BRIEFING'!B54 -> SERVIÇO EM FORRO | AA38: =D38/(O38/M38) -> #DIV/0!
B39: ='1. BRIEFING'!B55 -> FORNECIMENTO E INSTALAÇÃO DE FORRO EM GESSO | C39: ='1. BRIEFING'!C48 -> UN | D39: ='1. BRIEFING'!D48 -> 1 | O39: 8 | P39: =ROUNDUP(AA39,0) -> #DIV/0! | R39: =P39/Q39 -> #DIV/0! | S39: =E39*$R39 -> #DIV/0! | T39: =F39*$R39 -> #DIV/0! | U39: =G39*$R39 -> #DIV/0! | V39: =H39*$R39 -> #DIV/0! | W39: =I39*$R39 -> #DIV/0! | X39: =J39*$R39 -> #DIV/0! | Y39: =K39*$R39 -> #DIV/0! | Z39: =L39*$R39 -> #DIV/0! | AA39: =D39/(O39/M39) -> #DIV/0!
B40: ='1. BRIEFING'!B56 -> FORNECIMENTO E INSTALAÇÃO DE JUNTA EM DILATAÇÃO 3X3 CM | C40: ='1. BRIEFING'!C49 -> UN | D40: ='1. BRIEFING'!D49 -> 1 | O40: 8 | P40: =ROUNDUP(AA40,0) -> #DIV/0! | R40: =P40/Q40 -> #DIV/0! | S40: =E40*$R40 -> #DIV/0! | T40: =F40*$R40 -> #DIV/0! | U40: =G40*$R40 -> #DIV/0! | V40: =H40*$R40 -> #DIV/0! | W40: =I40*$R40 -> #DIV/0! | X40: =J40*$R40 -> #DIV/0! | Y40: =K40*$R40 -> #DIV/0! | Z40: =L40*$R40 -> #DIV/0! | AA40: =D40/(O40/M40) -> #DIV/0!
B41: ='1. BRIEFING'!B57 -> FORNECIMENTO E INSTALAÇÃO DE CORTINEIRO | C41: ='1. BRIEFING'!C50 -> UN | D41: ='1. BRIEFING'!D50 -> 1 | O41: 8 | P41: =ROUNDUP(AA41,0) -> #DIV/0! | R41: =P41/Q41 -> #DIV/0! | S41: =E41*$R41 -> #DIV/0! | T41: =F41*$R41 -> #DIV/0! | U41: =G41*$R41 -> #DIV/0! | V41: =H41*$R41 -> #DIV/0! | W41: =I41*$R41 -> #DIV/0! | X41: =J41*$R41 -> #DIV/0! | Y41: =K41*$R41 -> #DIV/0! | Z41: =L41*$R41 -> #DIV/0! | AA41: =D41/(O41/M41) -> #DIV/0!
B42: ='1. BRIEFING'!B58 -> FORNECIMENTO E INSTALAÇÃO DE SANCAS | C42: ='1. BRIEFING'!C51 -> UN | D42: ='1. BRIEFING'!D51 -> 1 | O42: 8 | P42: =ROUNDUP(AA42,0) -> #DIV/0! | R42: =P42/Q42 -> #DIV/0! | S42: =E42*$R42 -> #DIV/0! | T42: =F42*$R42 -> #DIV/0! | U42: =G42*$R42 -> #DIV/0! | V42: =H42*$R42 -> #DIV/0! | W42: =I42*$R42 -> #DIV/0! | X42: =J42*$R42 -> #DIV/0! | Y42: =K42*$R42 -> #DIV/0! | Z42: =L42*$R42 -> #DIV/0! | AA42: =D42/(O42/M42) -> #DIV/0!
B43: ='1. BRIEFING'!B59 -> SERVIÇO EM ESQUADRIA DE MADEIRA | AA43: =D43/(O43/M43) -> #DIV/0!
B44: ='1. BRIEFING'!B60 -> FORNECIMENTO E INSTALAÇÃO DE PORTA EM MADEIRA 0,60 x 2,10 m l COMPLETA | C44: ='1. BRIEFING'!C53 -> UN | D44: ='1. BRIEFING'!D53 -> 1 | O44: 8 | P44: =ROUNDUP(AA44,0) -> #DIV/0! | R44: =P44/Q44 -> #DIV/0! | S44: =E44*$R44 -> #DIV/0! | T44: =F44*$R44 -> #DIV/0! | U44: =G44*$R44 -> #DIV/0! | V44: =H44*$R44 -> #DIV/0! | W44: =I44*$R44 -> #DIV/0! | X44: =J44*$R44 -> #DIV/0! | Y44: =K44*$R44 -> #DIV/0! | Z44: =L44*$R44 -> #DIV/0! | AA44: =D44/(O44/M44) -> #DIV/0!
B45: ='1. BRIEFING'!B61 -> FORNECIMENTO E INSTALAÇÃO DE PORTA EM MADEIRA 0,70 X 2,10 M l COMPLETA | C45: ='1. BRIEFING'!C54 -> 0 | D45: ='1. BRIEFING'!D54 -> 0 | O45: 8 | P45: =ROUNDUP(AA45,0) -> #DIV/0! | R45: =P45/Q45 -> #DIV/0! | S45: =E45*$R45 -> #DIV/0! | T45: =F45*$R45 -> #DIV/0! | U45: =G45*$R45 -> #DIV/0! | V45: =H45*$R45 -> #DIV/0! | W45: =I45*$R45 -> #DIV/0! | X45: =J45*$R45 -> #DIV/0! | Y45: =K45*$R45 -> #DIV/0! | Z45: =L45*$R45 -> #DIV/0! | AA45: =D45/(O45/M45) -> #DIV/0!
B46: ='1. BRIEFING'!B62 -> FORNECIMENTO E INSTALAÇÃO DE PORTA EM MADEIRA 0,80 X 2,10 M l COMPLETA | C46: ='1. BRIEFING'!C55 -> M² | D46: ='1. BRIEFING'!D55 -> 1 | O46: 8 | P46: =ROUNDUP(AA46,0) -> #DIV/0! | R46: =P46/Q46 -> #DIV/0! | S46: =E46*$R46 -> #DIV/0! | T46: =F46*$R46 -> #DIV/0! | U46: =G46*$R46 -> #DIV/0! | V46: =H46*$R46 -> #DIV/0! | W46: =I46*$R46 -> #DIV/0! | X46: =J46*$R46 -> #DIV/0! | Y46: =K46*$R46 -> #DIV/0! | Z46: =L46*$R46 -> #DIV/0! | AA46: =D46/(O46/M46) -> #DIV/0!
B47: ='1. BRIEFING'!B63 -> FORNECIMENTO E INSTALAÇÃO DE PORTA EM MADEIRA 0,90 X 2,10 M l COMPLETA | C47: ='1. BRIEFING'!C56 -> M | D47: ='1. BRIEFING'!D56 -> 1 | O47: 8 | P47: =ROUNDUP(AA47,0) -> #DIV/0! | R47: =P47/Q47 -> #DIV/0! | S47: =E47*$R47 -> #DIV/0! | T47: =F47*$R47 -> #DIV/0! | U47: =G47*$R47 -> #DIV/0! | V47: =H47*$R47 -> #DIV/0! | W47: =I47*$R47 -> #DIV/0! | X47: =J47*$R47 -> #DIV/0! | Y47: =K47*$R47 -> #DIV/0! | Z47: =L47*$R47 -> #DIV/0! | AA47: =D47/(O47/M47) -> #DIV/0!
B48: ='1. BRIEFING'!B64 -> FORNECIMENTO E INSTALAÇÃO DE PORTA EM MADEIRA 0,90 X 2,10 M l COMPLETA | C48: ='1. BRIEFING'!C57 -> M | D48: ='1. BRIEFING'!D57 -> 1 | O48: 8 | P48: =ROUNDUP(AA48,0) -> #DIV/0! | R48: =P48/Q48 -> #DIV/0! | S48: =E48*$R48 -> #DIV/0! | T48: =F48*$R48 -> #DIV/0! | U48: =G48*$R48 -> #DIV/0! | V48: =H48*$R48 -> #DIV/0! | W48: =I48*$R48 -> #DIV/0! | X48: =J48*$R48 -> #DIV/0! | Y48: =K48*$R48 -> #DIV/0! | Z48: =L48*$R48 -> #DIV/0! | AA48: =D48/(O48/M48) -> #DIV/0!
B49: ='1. BRIEFING'!B65 -> FORNECIMENTO E INSTALAÇÃO DE PORTA EM MADEIRA 0,90 X 2,10 M l COMPLETA | C49: ='1. BRIEFING'!C58 -> M | D49: ='1. BRIEFING'!D58 -> 1 | O49: 8 | P49: =ROUNDUP(AA49,0) -> #DIV/0! | R49: =P49/Q49 -> #DIV/0! | S49: =E49*$R49 -> #DIV/0! | T49: =F49*$R49 -> #DIV/0! | U49: =G49*$R49 -> #DIV/0! | V49: =H49*$R49 -> #DIV/0! | W49: =I49*$R49 -> #DIV/0! | X49: =J49*$R49 -> #DIV/0! | Y49: =K49*$R49 -> #DIV/0! | Z49: =L49*$R49 -> #DIV/0! | AA49: =D49/(O49/M49) -> #DIV/0!
B50: ='1. BRIEFING'!B66 -> SERVIÇO DE MARMORARIA | AA50: =D50/(O50/M50) -> #DIV/0!
B51: ='1. BRIEFING'!B67 -> FORNECIMENTO E INSTALAÇÃO DE BANCADA EM GRANITO | C51: ='1. BRIEFING'!C60 -> UN | D51: ='1. BRIEFING'!D60 -> 1 | O51: 8 | P51: =ROUNDUP(AA51,0) -> #DIV/0! | R51: =P51/Q51 -> #DIV/0! | S51: =E51*$R51 -> #DIV/0! | T51: =F51*$R51 -> #DIV/0! | U51: =G51*$R51 -> #DIV/0! | V51: =H51*$R51 -> #DIV/0! | W51: =I51*$R51 -> #DIV/0! | X51: =J51*$R51 -> #DIV/0! | Y51: =K51*$R51 -> #DIV/0! | Z51: =L51*$R51 -> #DIV/0! | AA51: =D51/(O51/M51) -> #DIV/0!
B52: ='1. BRIEFING'!B68 -> FORNECIMENTO E INSTALAÇÃO DE NICHO EM GRANITO | C52: ='1. BRIEFING'!C61 -> UN | D52: ='1. BRIEFING'!D61 -> 1 | O52: 8 | P52: =ROUNDUP(AA52,0) -> #DIV/0! | R52: =P52/Q52 -> #DIV/0! | S52: =E52*$R52 -> #DIV/0! | T52: =F52*$R52 -> #DIV/0! | U52: =G52*$R52 -> #DIV/0! | V52: =H52*$R52 -> #DIV/0! | W52: =I52*$R52 -> #DIV/0! | X52: =J52*$R52 -> #DIV/0! | Y52: =K52*$R52 -> #DIV/0! | Z52: =L52*$R52 -> #DIV/0! | AA52: =D52/(O52/M52) -> #DIV/0!
B53: ='1. BRIEFING'!B69 -> FORNECIMENTO E INSTALAÇÃO DE DIVBOX EM GRANITO | C53: ='1. BRIEFING'!C62 -> UN | D53: ='1. BRIEFING'!D62 -> 1 | O53: 8 | P53: =ROUNDUP(AA53,0) -> #DIV/0! | R53: =P53/Q53 -> #DIV/0! | S53: =E53*$R53 -> #DIV/0! | T53: =F53*$R53 -> #DIV/0! | U53: =G53*$R53 -> #DIV/0! | V53: =H53*$R53 -> #DIV/0! | W53: =I53*$R53 -> #DIV/0! | X53: =J53*$R53 -> #DIV/0! | Y53: =K53*$R53 -> #DIV/0! | Z53: =L53*$R53 -> #DIV/0! | AA53: =D53/(O53/M53) -> #DIV/0!
B54: ='1. BRIEFING'!B70 -> FORNECIMENTO E INSTALAÇÃO DE NICHO EM GRANITO | C54: ='1. BRIEFING'!C63 -> UN | D54: ='1. BRIEFING'!D63 -> 1 | O54: 8 | P54: =ROUNDUP(AA54,0) -> #DIV/0! | R54: =P54/Q54 -> #DIV/0! | S54: =E54*$R54 -> #DIV/0! | T54: =F54*$R54 -> #DIV/0! | U54: =G54*$R54 -> #DIV/0! | V54: =H54*$R54 -> #DIV/0! | W54: =I54*$R54 -> #DIV/0! | X54: =J54*$R54 -> #DIV/0! | Y54: =K54*$R54 -> #DIV/0! | Z54: =L54*$R54 -> #DIV/0! | AA54: =D54/(O54/M54) -> #DIV/0!
B55: ='1. BRIEFING'!B71 -> REVESTIMENTO EM ARGAMASSA | AA55: =D55/(O55/M55) -> #DIV/0!
B56: ='1. BRIEFING'!B72 -> APLICAÇÃO DE CHAPISCO E REBOCO EM PAREDE DE ALVENARIA NOVA | C56: ='1. BRIEFING'!C65 -> UN | D56: ='1. BRIEFING'!D65 -> 1 | O56: 8 | P56: =ROUNDUP(AA56,0) -> #DIV/0! | R56: =P56/Q56 -> #DIV/0! | S56: =E56*$R56 -> #DIV/0! | T56: =F56*$R56 -> #DIV/0! | U56: =G56*$R56 -> #DIV/0! | V56: =H56*$R56 -> #DIV/0! | W56: =I56*$R56 -> #DIV/0! | X56: =J56*$R56 -> #DIV/0! | Y56: =K56*$R56 -> #DIV/0! | Z56: =L56*$R56 -> #DIV/0! | AA56: =D56/(O56/M56) -> #DIV/0!
B57: ='1. BRIEFING'!B73 -> REGULARIZAÇÃO COM REBOCO FINO PARA RECEBIMENTO DE REVESTIMENTO NOVO | C57: ='1. BRIEFING'!C66 -> 0 | D57: ='1. BRIEFING'!D66 -> 0 | O57: 8 | P57: =ROUNDUP(AA57,0) -> #DIV/0! | R57: =P57/Q57 -> #DIV/0! | S57: =E57*$R57 -> #DIV/0! | T57: =F57*$R57 -> #DIV/0! | U57: =G57*$R57 -> #DIV/0! | V57: =H57*$R57 -> #DIV/0! | W57: =I57*$R57 -> #DIV/0! | X57: =J57*$R57 -> #DIV/0! | Y57: =K57*$R57 -> #DIV/0! | Z57: =L57*$R57 -> #DIV/0! | AA57: =D57/(O57/M57) -> #DIV/0!
B58: ='1. BRIEFING'!B74 -> REGULARIZAÇÃO DE PISO COM ATÉ 5 CM PARA RECEBIMENTO DE REVESTIMENTO NONO | C58: ='1. BRIEFING'!C67 -> VB | D58: ='1. BRIEFING'!D67 -> 1 | O58: 8 | P58: =ROUNDUP(AA58,0) -> #DIV/0! | R58: =P58/Q58 -> #DIV/0! | S58: =E58*$R58 -> #DIV/0! | T58: =F58*$R58 -> #DIV/0! | U58: =G58*$R58 -> #DIV/0! | V58: =H58*$R58 -> #DIV/0! | W58: =I58*$R58 -> #DIV/0! | X58: =J58*$R58 -> #DIV/0! | Y58: =K58*$R58 -> #DIV/0! | Z58: =L58*$R58 -> #DIV/0! | AA58: =D58/(O58/M58) -> #DIV/0!
B59: ='1. BRIEFING'!B75 -> REVESTIMENTO EM PORCELANATO | AA59: =D59/(O59/M59) -> #DIV/0!
B60: ='1. BRIEFING'!B76 -> REVESTIMENTO EM PISO ÁREA COMUM l BIANCOGRÉS CRISTALLO 60X60 CM | C60: M² | D60: ='1. BRIEFING'!D69 -> 1 | O60: 8 | P60: =ROUNDUP(AA60,0) -> #DIV/0! | R60: =P60/Q60 -> #DIV/0! | S60: =E60*$R60 -> #DIV/0! | T60: =F60*$R60 -> #DIV/0! | U60: =G60*$R60 -> #DIV/0! | V60: =H60*$R60 -> #DIV/0! | W60: =I60*$R60 -> #DIV/0! | X60: =J60*$R60 -> #DIV/0! | Y60: =K60*$R60 -> #DIV/0! | Z60: =L60*$R60 -> #DIV/0! | AA60: =D60/(O60/M60) -> #DIV/0!
B61: ='1. BRIEFING'!B77 -> REVESTIMENTO EM PISO ÁREA MOLHADA l BIANCOGRÉS CRISTALLO 60X60 CM | C61: ='1. BRIEFING'!C70 -> VB | D61: ='1. BRIEFING'!D70 -> 1 | O61: 8 | P61: =ROUNDUP(AA61,0) -> #DIV/0! | R61: =P61/Q61 -> #DIV/0! | S61: =E61*$R61 -> #DIV/0! | T61: =F61*$R61 -> #DIV/0! | U61: =G61*$R61 -> #DIV/0! | V61: =H61*$R61 -> #DIV/0! | W61: =I61*$R61 -> #DIV/0! | X61: =J61*$R61 -> #DIV/0! | Y61: =K61*$R61 -> #DIV/0! | Z61: =L61*$R61 -> #DIV/0! | AA61: =D61/(O61/M61) -> #DIV/0!
B62: ='1. BRIEFING'!B78 -> REVESTIMENTO EM PAREDE COZINHA l POINTER 60X60 CM | C62: ='1. BRIEFING'!C71 -> 0 | D62: ='1. BRIEFING'!D71 -> 0 | O62: 8 | P62: =ROUNDUP(AA62,0) -> #DIV/0! | R62: =P62/Q62 -> #DIV/0! | S62: =E62*$R62 -> #DIV/0! | T62: =F62*$R62 -> #DIV/0! | U62: =G62*$R62 -> #DIV/0! | V62: =H62*$R62 -> #DIV/0! | W62: =I62*$R62 -> #DIV/0! | X62: =J62*$R62 -> #DIV/0! | Y62: =K62*$R62 -> #DIV/0! | Z62: =L62*$R62 -> #DIV/0! | AA62: =D62/(O62/M62) -> #DIV/0!
B63: ='1. BRIEFING'!B79 -> REVESTIMENTO EM PAREDE BANHEIROS l POINTER 60X60 CM | C63: ='1. BRIEFING'!C72 -> M² | D63: ='1. BRIEFING'!D72 -> 1 | O63: 8 | P63: =ROUNDUP(AA63,0) -> #DIV/0! | R63: =P63/Q63 -> #DIV/0! | S63: =E63*$R63 -> #DIV/0! | T63: =F63*$R63 -> #DIV/0! | U63: =G63*$R63 -> #DIV/0! | V63: =H63*$R63 -> #DIV/0! | W63: =I63*$R63 -> #DIV/0! | X63: =J63*$R63 -> #DIV/0! | Y63: =K63*$R63 -> #DIV/0! | Z63: =L63*$R63 -> #DIV/0! | AA63: =D63/(O63/M63) -> #DIV/0!
B64: ='1. BRIEFING'!B80 -> REVESTIMENTO EM PAREDE ÁREA DE SERVIÇO l POINTER 60X60 CM | C64: ='1. BRIEFING'!C73 -> M² | D64: ='1. BRIEFING'!D73 -> 1 | O64: 8 | P64: =ROUNDUP(AA64,0) -> #DIV/0! | R64: =P64/Q64 -> #DIV/0! | S64: =E64*$R64 -> #DIV/0! | T64: =F64*$R64 -> #DIV/0! | U64: =G64*$R64 -> #DIV/0! | V64: =H64*$R64 -> #DIV/0! | W64: =I64*$R64 -> #DIV/0! | X64: =J64*$R64 -> #DIV/0! | Y64: =K64*$R64 -> #DIV/0! | Z64: =L64*$R64 -> #DIV/0! | AA64: =D64/(O64/M64) -> #DIV/0!
B65: ='1. BRIEFING'!B81 -> REVESTIMENTO EM PAREDE VARANDA l POINTER 60X60 CM | C65: ='1. BRIEFING'!C74 -> M² | D65: ='1. BRIEFING'!D74 -> 1 | O65: 8 | P65: =ROUNDUP(AA65,0) -> #DIV/0! | R65: =P65/Q65 -> #DIV/0! | S65: =E65*$R65 -> #DIV/0! | T65: =F65*$R65 -> #DIV/0! | U65: =G65*$R65 -> #DIV/0! | V65: =H65*$R65 -> #DIV/0! | W65: =I65*$R65 -> #DIV/0! | X65: =J65*$R65 -> #DIV/0! | Y65: =K65*$R65 -> #DIV/0! | Z65: =L65*$R65 -> #DIV/0! | AA65: =D65/(O65/M65) -> #DIV/0!
B66: ='1. BRIEFING'!B82 -> LOUÇAS E METAIS | AA66: =D66/(O66/M66) -> #DIV/0!
B67: ='1. BRIEFING'!B83 -> INSTALAÇÃO DE VASO SANITÁRIO COM CX ACOPLADA l ECOLUS CELITE BRANCA | C67: ='1. BRIEFING'!C76 -> M² | D67: ='1. BRIEFING'!D76 -> 1 | O67: 8 | P67: =ROUNDUP(AA67,0) -> #DIV/0! | R67: =P67/Q67 -> #DIV/0! | S67: =E67*$R67 -> #DIV/0! | T67: =F67*$R67 -> #DIV/0! | U67: =G67*$R67 -> #DIV/0! | V67: =H67*$R67 -> #DIV/0! | W67: =I67*$R67 -> #DIV/0! | X67: =J67*$R67 -> #DIV/0! | Y67: =K67*$R67 -> #DIV/0! | Z67: =L67*$R67 -> #DIV/0! | AA67: =D67/(O67/M67) -> #DIV/0!
B68: ='1. BRIEFING'!B84 -> INSTALAÇÃO DE CUBA SUSPENSA DE CANTO EM LOUÇA BRANCA l CELITE | C68: ='1. BRIEFING'!C77 -> M² | D68: ='1. BRIEFING'!D77 -> 1 | O68: 8 | P68: =ROUNDUP(AA68,0) -> #DIV/0! | R68: =P68/Q68 -> #DIV/0! | S68: =E68*$R68 -> #DIV/0! | T68: =F68*$R68 -> #DIV/0! | U68: =G68*$R68 -> #DIV/0! | V68: =H68*$R68 -> #DIV/0! | W68: =I68*$R68 -> #DIV/0! | X68: =J68*$R68 -> #DIV/0! | Y68: =K68*$R68 -> #DIV/0! | Z68: =L68*$R68 -> #DIV/0! | AA68: =D68/(O68/M68) -> #DIV/0!
B69: ='1. BRIEFING'!B85 -> INSTALAÇÃO DE TORNEIRA BICA ALTA | C69: ='1. BRIEFING'!C78 -> M² | D69: ='1. BRIEFING'!D78 -> 1 | O69: 8 | P69: =ROUNDUP(AA69,0) -> #DIV/0! | R69: =P69/Q69 -> #DIV/0! | S69: =E69*$R69 -> #DIV/0! | T69: =F69*$R69 -> #DIV/0! | U69: =G69*$R69 -> #DIV/0! | V69: =H69*$R69 -> #DIV/0! | W69: =I69*$R69 -> #DIV/0! | X69: =J69*$R69 -> #DIV/0! | Y69: =K69*$R69 -> #DIV/0! | Z69: =L69*$R69 -> #DIV/0! | AA69: =D69/(O69/M69) -> #DIV/0!
B70: ='1. BRIEFING'!B86 -> INSTALAÇÃO DE PORTA ACESSÓRIOS l KIT BANHEIRO | C70: ='1. BRIEFING'!C79 -> M² | D70: ='1. BRIEFING'!D79 -> 1 | O70: 8 | P70: =ROUNDUP(AA70,0) -> #DIV/0! | R70: =P70/Q70 -> #DIV/0! | S70: =E70*$R70 -> #DIV/0! | T70: =F70*$R70 -> #DIV/0! | U70: =G70*$R70 -> #DIV/0! | V70: =H70*$R70 -> #DIV/0! | W70: =I70*$R70 -> #DIV/0! | X70: =J70*$R70 -> #DIV/0! | Y70: =K70*$R70 -> #DIV/0! | Z70: =L70*$R70 -> #DIV/0! | AA70: =D70/(O70/M70) -> #DIV/0!
B71: ='1. BRIEFING'!B87 -> INSTALAÇÃO DE DUCHA HIGIÊNCIA | C71: ='1. BRIEFING'!C80 -> M² | D71: ='1. BRIEFING'!D80 -> 1 | O71: 8 | P71: =ROUNDUP(AA71,0) -> #DIV/0! | R71: =P71/Q71 -> #DIV/0! | S71: =E71*$R71 -> #DIV/0! | T71: =F71*$R71 -> #DIV/0! | U71: =G71*$R71 -> #DIV/0! | V71: =H71*$R71 -> #DIV/0! | W71: =I71*$R71 -> #DIV/0! | X71: =J71*$R71 -> #DIV/0! | Y71: =K71*$R71 -> #DIV/0! | Z71: =L71*$R71 -> #DIV/0! | AA71: =D71/(O71/M71) -> #DIV/0!
B72: ='1. BRIEFING'!B88 -> INSTALAÇÃO DE CHUVEIRO | C72: ='1. BRIEFING'!C81 -> M² | D72: ='1. BRIEFING'!D81 -> 1 | O72: 8 | P72: =ROUNDUP(AA72,0) -> #DIV/0! | R72: =P72/Q72 -> #DIV/0! | S72: =E72*$R72 -> #DIV/0! | T72: =F72*$R72 -> #DIV/0! | U72: =G72*$R72 -> #DIV/0! | V72: =H72*$R72 -> #DIV/0! | W72: =I72*$R72 -> #DIV/0! | X72: =J72*$R72 -> #DIV/0! | Y72: =K72*$R72 -> #DIV/0! | Z72: =L72*$R72 -> #DIV/0! | AA72: =D72/(O72/M72) -> #DIV/0!
B73: ='1. BRIEFING'!B89 -> SERVIÇO EM PINTURA | AA73: =D73/(O73/M73) -> #DIV/0!
B74: ='1. BRIEFING'!B90 -> APLICAÇÃO DE SELADOR ACRILICO PAREDE E FORRO | C74: ='1. BRIEFING'!C83 -> UN | D74: ='1. BRIEFING'!D83 -> 1 | O74: 8 | P74: =ROUNDUP(AA74,0) -> #DIV/0! | R74: =P74/Q74 -> #DIV/0! | S74: =E74*$R74 -> #DIV/0! | T74: =F74*$R74 -> #DIV/0! | U74: =G74*$R74 -> #DIV/0! | V74: =H74*$R74 -> #DIV/0! | W74: =I74*$R74 -> #DIV/0! | X74: =J74*$R74 -> #DIV/0! | Y74: =K74*$R74 -> #DIV/0! | Z74: =L74*$R74 -> #DIV/0! | AA74: =D74/(O74/M74) -> #DIV/0!
B75: ='1. BRIEFING'!B91 -> APLICAÇÃO E LIXAMENTO DE MASSA CORRIDA EM FORRO DE GESSO | C75: ='1. BRIEFING'!C84 -> UN | D75: ='1. BRIEFING'!D84 -> 1 | O75: 8 | P75: =ROUNDUP(AA75,0) -> #DIV/0! | R75: =P75/Q75 -> #DIV/0! | S75: =E75*$R75 -> #DIV/0! | T75: =F75*$R75 -> #DIV/0! | U75: =G75*$R75 -> #DIV/0! | V75: =H75*$R75 -> #DIV/0! | W75: =I75*$R75 -> #DIV/0! | X75: =J75*$R75 -> #DIV/0! | Y75: =K75*$R75 -> #DIV/0! | Z75: =L75*$R75 -> #DIV/0! | AA75: =D75/(O75/M75) -> #DIV/0!
B76: ='1. BRIEFING'!B92 -> APLICAÇÃO DE TINTA EM FORRO EM GESSO COM TINA ACRÍLLICA ACETINADO NA COR | C76: ='1. BRIEFING'!C85 -> UN | D76: ='1. BRIEFING'!D85 -> 1 | O76: 8 | P76: =ROUNDUP(AA76,0) -> #DIV/0! | R76: =P76/Q76 -> #DIV/0! | S76: =E76*$R76 -> #DIV/0! | T76: =F76*$R76 -> #DIV/0! | U76: =G76*$R76 -> #DIV/0! | V76: =H76*$R76 -> #DIV/0! | W76: =I76*$R76 -> #DIV/0! | X76: =J76*$R76 -> #DIV/0! | Y76: =K76*$R76 -> #DIV/0! | Z76: =L76*$R76 -> #DIV/0! | AA76: =D76/(O76/M76) -> #DIV/0!
B77: ='1. BRIEFING'!B93 -> APLICAÇÃO E LIXAMENTO DE MASSA CORRIDA EM PAREDE | C77: ='1. BRIEFING'!C86 -> UN | D77: ='1. BRIEFING'!D86 -> 1 | O77: 8 | P77: =ROUNDUP(AA77,0) -> #DIV/0! | R77: =P77/Q77 -> #DIV/0! | S77: =E77*$R77 -> #DIV/0! | T77: =F77*$R77 -> #DIV/0! | U77: =G77*$R77 -> #DIV/0! | V77: =H77*$R77 -> #DIV/0! | W77: =I77*$R77 -> #DIV/0! | X77: =J77*$R77 -> #DIV/0! | Y77: =K77*$R77 -> #DIV/0! | Z77: =L77*$R77 -> #DIV/0! | AA77: =D77/(O77/M77) -> #DIV/0!
B78: ='1. BRIEFING'!B94 -> APLICAÇÃO DE TINTA ACRÍLICA EM PAREDE , ACETINADO COR | C78: ='1. BRIEFING'!C87 -> UN | D78: ='1. BRIEFING'!D87 -> 1 | O78: 8 | P78: =ROUNDUP(AA78,0) -> #DIV/0! | R78: =P78/Q78 -> #DIV/0! | S78: =E78*$R78 -> #DIV/0! | T78: =F78*$R78 -> #DIV/0! | U78: =G78*$R78 -> #DIV/0! | V78: =H78*$R78 -> #DIV/0! | W78: =I78*$R78 -> #DIV/0! | X78: =J78*$R78 -> #DIV/0! | Y78: =K78*$R78 -> #DIV/0! | Z78: =L78*$R78 -> #DIV/0! | AA78: =D78/(O78/M78) -> #DIV/0!
B79: ='1. BRIEFING'!B95 -> APLICAÇÃO DE FUNDO, MASSA E TINTA EM PORTA DE MADEIRA, ACETINADO NA COR | C79: ='1. BRIEFING'!C88 -> UN | D79: ='1. BRIEFING'!D88 -> 1 | O79: 8 | P79: =ROUNDUP(AA79,0) -> #DIV/0! | R79: =P79/Q79 -> #DIV/0! | S79: =E79*$R79 -> #DIV/0! | T79: =F79*$R79 -> #DIV/0! | U79: =G79*$R79 -> #DIV/0! | V79: =H79*$R79 -> #DIV/0! | W79: =I79*$R79 -> #DIV/0! | X79: =J79*$R79 -> #DIV/0! | Y79: =K79*$R79 -> #DIV/0! | Z79: =L79*$R79 -> #DIV/0! | AA79: =D79/(O79/M79) -> #DIV/0!
B80: ='1. BRIEFING'!B96 -> LIMPEZA FINAL | AA80: =D80/(O80/M80) -> #DIV/0!
B81: ='1. BRIEFING'!B97 -> LIMPEZA FINAL DA OBRA | C81: ='1. BRIEFING'!C90 -> M2 | D81: ='1. BRIEFING'!D90 -> 1 | O81: 8 | P81: =ROUNDUP(AA81,0) -> #DIV/0! | R81: =P81/Q81 -> #DIV/0! | S81: =E81*$R81 -> #DIV/0! | T81: =F81*$R81 -> #DIV/0! | U81: =G81*$R81 -> #DIV/0! | V81: =H81*$R81 -> #DIV/0! | W81: =I81*$R81 -> #DIV/0! | X81: =J81*$R81 -> #DIV/0! | Y81: =K81*$R81 -> #DIV/0! | Z81: =L81*$R81 -> #DIV/0! | AA81: =D81/(O81/M81) -> #DIV/0!
B82: ='1. BRIEFING'!B98 -> REMOÇÃO DE ENTULHOS GERADOS PELA OBRA POR CARRO PEQUENOS | C82: ='1. BRIEFING'!C91 -> M2 | D82: ='1. BRIEFING'!D91 -> 1 | O82: 8 | P82: =ROUNDUP(AA82,0) -> #DIV/0! | R82: =P82/Q82 -> #DIV/0! | S82: =E82*$R82 -> #DIV/0! | T82: =F82*$R82 -> #DIV/0! | U82: =G82*$R82 -> #DIV/0! | V82: =H82*$R82 -> #DIV/0! | W82: =I82*$R82 -> #DIV/0! | X82: =J82*$R82 -> #DIV/0! | Y82: =K82*$R82 -> #DIV/0! | Z82: =L82*$R82 -> #DIV/0! | AA82: =D82/(O82/M82) -> #DIV/0!
B83: ='1. BRIEFING'!B99 -> 0 | P83: =ROUNDUP(AA83,0) -> #DIV/0! | R83: =P83/Q83 -> #DIV/0! | S83: =E83*$R83 -> #DIV/0! | T83: =F83*$R83 -> #DIV/0! | U83: =G83*$R83 -> #DIV/0! | V83: =H83*$R83 -> #DIV/0! | W83: =I83*$R83 -> #DIV/0! | X83: =J83*$R83 -> #DIV/0! | Y83: =K83*$R83 -> #DIV/0! | Z83: =L83*$R83 -> #DIV/0! | AA83: =D83/(O83/M83) -> #DIV/0!
B84: ='1. BRIEFING'!B100 -> 0 | P84: =ROUNDUP(AA84,0) -> #DIV/0! | R84: =P84/Q84 -> #DIV/0! | S84: =E84*$R84 -> #DIV/0! | T84: =F84*$R84 -> #DIV/0! | U84: =G84*$R84 -> #DIV/0! | V84: =H84*$R84 -> #DIV/0! | W84: =I84*$R84 -> #DIV/0! | X84: =J84*$R84 -> #DIV/0! | Y84: =K84*$R84 -> #DIV/0! | Z84: =L84*$R84 -> #DIV/0! | AA84: =D84/(O84/M84) -> #DIV/0!
P85: =ROUNDUP(AA85,0) -> #DIV/0! | R85: =P85/Q85 -> #DIV/0! | S85: =E85*$R85 -> #DIV/0! | T85: =F85*$R85 -> #DIV/0! | U85: =G85*$R85 -> #DIV/0! | V85: =H85*$R85 -> #DIV/0! | W85: =I85*$R85 -> #DIV/0! | X85: =J85*$R85 -> #DIV/0! | Y85: =K85*$R85 -> #DIV/0! | Z85: =L85*$R85 -> #DIV/0! | AA85: =D85/(O85/M85) -> #DIV/0!
P86: =ROUNDUP(AA86,0) -> #DIV/0! | R86: =P86/Q86 -> #DIV/0! | S86: =E86*$R86 -> #DIV/0! | T86: =F86*$R86 -> #DIV/0! | U86: =G86*$R86 -> #DIV/0! | V86: =H86*$R86 -> #DIV/0! | W86: =I86*$R86 -> #DIV/0! | X86: =J86*$R86 -> #DIV/0! | Y86: =K86*$R86 -> #DIV/0! | Z86: =L86*$R86 -> #DIV/0! | AA86: =D86/(O86/M86) -> #DIV/0!
P87: =ROUNDUP(AA87,0) -> #DIV/0! | R87: =P87/Q87 -> #DIV/0! | S87: =E87*$R87 -> #DIV/0! | T87: =F87*$R87 -> #DIV/0! | U87: =G87*$R87 -> #DIV/0! | V87: =H87*$R87 -> #DIV/0! | W87: =I87*$R87 -> #DIV/0! | X87: =J87*$R87 -> #DIV/0! | Y87: =K87*$R87 -> #DIV/0! | Z87: =L87*$R87 -> #DIV/0! | AA87: =D87/(O87/M87) -> #DIV/0!
P88: =ROUNDUP(AA88,0) -> #DIV/0! | R88: =P88/Q88 -> #DIV/0! | S88: =E88*$R88 -> #DIV/0! | T88: =F88*$R88 -> #DIV/0! | U88: =G88*$R88 -> #DIV/0! | V88: =H88*$R88 -> #DIV/0! | W88: =I88*$R88 -> #DIV/0! | X88: =J88*$R88 -> #DIV/0! | Y88: =K88*$R88 -> #DIV/0! | Z88: =L88*$R88 -> #DIV/0! | AA88: =D88/(O88/M88) -> #DIV/0!
P89: =ROUNDUP(AA89,0) -> #DIV/0! | R89: =P89/Q89 -> #DIV/0! | S89: =E89*$R89 -> #DIV/0! | T89: =F89*$R89 -> #DIV/0! | U89: =G89*$R89 -> #DIV/0! | V89: =H89*$R89 -> #DIV/0! | W89: =I89*$R89 -> #DIV/0! | X89: =J89*$R89 -> #DIV/0! | Y89: =K89*$R89 -> #DIV/0! | Z89: =L89*$R89 -> #DIV/0! | AA89: =D89/(O89/M89) -> #DIV/0!
P90: =ROUNDUP(AA90,0) -> #DIV/0! | R90: =P90/Q90 -> #DIV/0! | S90: =E90*$R90 -> #DIV/0! | T90: =F90*$R90 -> #DIV/0! | U90: =G90*$R90 -> #DIV/0! | V90: =H90*$R90 -> #DIV/0! | W90: =I90*$R90 -> #DIV/0! | X90: =J90*$R90 -> #DIV/0! | Y90: =K90*$R90 -> #DIV/0! | Z90: =L90*$R90 -> #DIV/0! | AA90: =D90/(O90/M90) -> #DIV/0!
P91: =ROUNDUP(AA91,0) -> #DIV/0! | R91: =P91/Q91 -> #DIV/0! | S91: =E91*$R91 -> #DIV/0! | T91: =F91*$R91 -> #DIV/0! | U91: =G91*$R91 -> #DIV/0! | V91: =H91*$R91 -> #DIV/0! | W91: =I91*$R91 -> #DIV/0! | X91: =J91*$R91 -> #DIV/0! | Y91: =K91*$R91 -> #DIV/0! | Z91: =L91*$R91 -> #DIV/0! | AA91: =D91/(O91/M91) -> #DIV/0!
P92: =ROUNDUP(AA92,0) -> #DIV/0! | R92: =P92/Q92 -> #DIV/0! | S92: =E92*$R92 -> #DIV/0! | T92: =F92*$R92 -> #DIV/0! | U92: =G92*$R92 -> #DIV/0! | V92: =H92*$R92 -> #DIV/0! | W92: =I92*$R92 -> #DIV/0! | X92: =J92*$R92 -> #DIV/0! | Y92: =K92*$R92 -> #DIV/0! | Z92: =L92*$R92 -> #DIV/0! | AA92: =D92/(O92/M92) -> #DIV/0!
P93: =ROUNDUP(AA93,0) -> #DIV/0! | R93: =P93/Q93 -> #DIV/0! | S93: =E93*$R93 -> #DIV/0! | T93: =F93*$R93 -> #DIV/0! | U93: =G93*$R93 -> #DIV/0! | V93: =H93*$R93 -> #DIV/0! | W93: =I93*$R93 -> #DIV/0! | X93: =J93*$R93 -> #DIV/0! | Y93: =K93*$R93 -> #DIV/0! | Z93: =L93*$R93 -> #DIV/0! | AA93: =D93/(O93/M93) -> #DIV/0!
P94: =ROUNDUP(AA94,0) -> #DIV/0! | R94: =P94/Q94 -> #DIV/0! | S94: =E94*$R94 -> #DIV/0! | T94: =F94*$R94 -> #DIV/0! | U94: =G94*$R94 -> #DIV/0! | V94: =H94*$R94 -> #DIV/0! | W94: =I94*$R94 -> #DIV/0! | X94: =J94*$R94 -> #DIV/0! | Y94: =K94*$R94 -> #DIV/0! | Z94: =L94*$R94 -> #DIV/0! | AA94: =D94/(O94/M94) -> #DIV/0!
P95: =ROUNDUP(AA95,0) -> #DIV/0! | R95: =P95/Q95 -> #DIV/0! | S95: =E95*$R95 -> #DIV/0! | T95: =F95*$R95 -> #DIV/0! | U95: =G95*$R95 -> #DIV/0! | V95: =H95*$R95 -> #DIV/0! | W95: =I95*$R95 -> #DIV/0! | X95: =J95*$R95 -> #DIV/0! | Y95: =K95*$R95 -> #DIV/0! | Z95: =L95*$R95 -> #DIV/0! | AA95: =D95/(O95/M95) -> #DIV/0!
P96: =ROUNDUP(AA96,0) -> #DIV/0! | R96: =P96/Q96 -> #DIV/0! | S96: =E96*$R96 -> #DIV/0! | T96: =F96*$R96 -> #DIV/0! | U96: =G96*$R96 -> #DIV/0! | V96: =H96*$R96 -> #DIV/0! | W96: =I96*$R96 -> #DIV/0! | X96: =J96*$R96 -> #DIV/0! | Y96: =K96*$R96 -> #DIV/0! | Z96: =L96*$R96 -> #DIV/0! | AA96: =D96/(O96/M96) -> #DIV/0!
... P107: =ROUNDUP(AA107,0) -> #DIV/0! | R107: =P107/Q107 -> #DIV/0! | S107: =E107*$R107 -> #DIV/0! | T107: =F107*$R107 -> #DIV/0! | U107: =G107*$R107 -> #DIV/0! | V107: =H107*$R107 -> #DIV/0! | W107: =I107*$R107 -> #DIV/0! | X107: =J107*$R107 -> #DIV/0! | Y107: =K107*$R107 -> #DIV/0! | Z107: =L107*$R107 -> #DIV/0! | AA107: =D107/(O107/M107) -> #DIV/0!

Sheet 0. P. VENDA
B3: RESUMO ORÇAMENTO | H3: DESTRINCHADO
A4: 1 | B4: CUSTO DIRETO | C4: ='4. PLAN ORÇA'!M94 -> 28880.24 | D4: =C4/C7 -> 1 | H4: PREÇO DE VENDA | I4: =C27 -> 39662.196
A5: 2 | B5: CUSTO INDIRETO | C5: ='4. CUSTO IND'!H2 -> 0 | D5: =C5/C7 -> 0
H6: COMISSÃO | I6: =I4*J6 -> 396.62196 | J6: 0.01
A7: 3 | B7: TOTAL CD+CI | C7: =SUM(C4,C5) -> 28880.24
H8: TRIBUTOS | I8: =I4*C22 -> 1983.1098 | J8: =C22 -> 0.05
A9: 4 | B9: ADM CENTRAL | C9: =C7*D9 -> 288.8024 | D9: 0.01 | E9: =SUM(C9:C11) -> 866.4072
A10: 5 | B10: CUSTO FINANC. | C10: =C7*D10 -> 288.8024 | D10: 0.01 | H10: LUCRO | I10: =(I4*C24)-I6 -> 7535.8173 | J10: =I10/I4 -> 0.19
A11: 6 | B11: IC SOBRE CD+CI | C11: =C7*D11 -> 288.8024 | D11: 0.01
H12: SALDO CUSTO | I12: =I4-I6-I8-I10 -> 29746.647 | J12: =I12/I4 -> 0.75
A13: 7 | B13: TOTAL CUSTO | C13: =SUM(C7+C9+C10+C11) -> 29746.647
H14: ADM CENTRAL | I14: =I12*D9 -> 297.46647
A15: 8 | B15: COFINS | C15: 0.015 | D15: =$C$27*C15 -> 594.93294 | H15: CUSTO FINANC | I15: =I12*D10 -> 297.46647
A16: 9 | B16: PIS | C16: 0 | D16: =$C$27*C16 -> 0 | H16: IMPREV E CONTIG | I16: =I12*D11 -> 297.46647
A17: 10 | B17: ICMS | C17: 0 | D17: =$C$27*C17 -> 0
A18: 11 | B18: ISS | C18: 0.02 | D18: =$C$27*C18 -> 793.24393 | H18: SALDO CUSTO | I18: =I12-(I14+I15+I16) -> 28854.248
A19: 12 | B19: IRPJ | C19: 0 | D19: =$C$27*C19 -> 0
A20: 13 | B20: CSLL | C20: 0.015 | D20: =$C$27*C20 -> 594.93294 | H20: CUSTO INDIRETO | I20: =I18*D5 -> 0 | J20: =I20/I18 -> 0
H21: CUSTO DIRETO | I21: =I18*D4 -> 28854.248 | J21: =I21/I18 -> 1
A22: 14 | B22: ALÍQUOTA % | C22: =SUM(C15:C20) -> 0.05 | D22: =SUM(D15:D20) -> 1983.1098 | E22: FAT ATÉ 180 K
H23: SALDO | I23: =I18-(I20+I21) -> 0
A24: 15 | B24: LUCRO | C24: 0.2 | D24: =C27*C24 -> 7932.4393 | E24: LUCRO LIQUIDO
A25: 16 | B25: IMPOST + LUCRO | C25: =SUM(C22,C24) -> 0.25 | D25: =SUM(D22+D24) -> 9915.5491
A27: 17 | B27: PREÇO DE VENDA | C27: =C13/(1-C25) -> 39662.196 | E27: UND
A28: 18 | B28: BDI | C28: =C27/C13-1 -> 0.33333333

Sheet PLANEJ FIN
B2: CRONOGRAMA FISICO-FINANCEIRO
D4: 05 - 08 DEZ | F4: 11 - 15 DEZ | H4: 18 - 22 DEZ | J4: GERAL
B5: CÓDIGO | C5: SERVIÇOS | D5: VALOR (R$) | E5: PERC. (%) | F5: VALOR (R$) | G5: PERC. (%) | H5: VALOR (R$) | I5: PERC. (%) | J5: TOTAL (%) | K5: VALOR (R$) | L5: VALOR C/ BDI (R$) | M5: PERC. (%)
C6: DESPESA ADMINISTRATIVA | D6: =L6*E6/100 -> #REF! | E6: 100 | J6: =E6+G6 -> 100 | K6: ='[1]R$ OBRA'!G19 -> #REF! | L6: =K6*1.4 -> #REF! | M6: =L6/$L$21 -> #REF!
B7: 1 | C7: ELETRICA
B8: 2 | C8: PONTO DE TOMADA RESIDENCIAL INCLUINDO TOMADA 10A/250V, CAIXA ELÉTRICA ELETRODUTO, CABO, RASGO, QUEBRA E CHUMBAMENTO. | D8: =L8*E8/100 -> #REF! | E8: 50 | F8: =$L8*G8/100 -> #REF! | G8: 0 | H8: =$L8*I8/100 -> #REF! | I8: 0 | J8: =E8+G8 -> 50 | K8: ='[1]R$ OBRA'!G29 -> #REF! | L8: =K8*1.4 -> #REF! | M8: =L8/$L$21 -> #REF!
B9: 3 | C9: REVESTIMENTO
B10: 4 | C10: REVESTIMENTO CERÂMICO PARA PISO COM PLACAS TIPO ESMALTADA EXTRA DE DIMENSÕES 35X35 CM APLICADA EM AMBIENTES DE ÁREA ENTRE 5 M2 E 10 M2 | D10: =L10*E10/100 -> #REF! | E10: 100 | F10: =$L10*G10/100 -> #REF! | G10: 0 | H10: =$L10*I10/100 -> #REF! | I10: 0 | J10: =E10+G10 -> 100 | K10: ='[1]R$ OBRA'!G49 -> #REF! | L10: =K10*1.4 -> #REF! | M10: =L10/$L$21 -> #REF!
B11: 5 | C11: PINTURA
B12: 6 | C12: APLICAÇÃO E LIXAMENTO DE MASSA LÁTEX EM PAREDES, DUAS DEMÃOS. | D12: =L12*E12/100 -> #VALUE! | E12: 0 | F12: =$L12*G12/100 -> #VALUE! | G12: 100 | H12: =$L12*I12/100 -> #VALUE! | I12: 100 | J12: =E12+G12 -> 100 | K12: #REF! | L12: =K12*1.4 -> #VALUE! | M12: =L12/$L$21 -> #VALUE!
B13: 7 | C13: APLICAÇÃO MANUAL DE PINTURA COM TINTA LÁTEX ACRÍLICA EM PAREDES, DUAS DEMÃOS. | D13: =L13*E13/100 -> #VALUE! | E13: 0 | F13: =$L13*G13/100 -> #VALUE! | G13: 100 | H13: =$L13*I13/100 -> #VALUE! | I13: 100 | J13: =E13+G13 -> 100 | K13: #REF! | L13: =K13*1.4 -> #VALUE! | M13: =L13/$L$21 -> #VALUE!
B14: 8 | C14: LIMPEZA FINAL
B15: 9 | C15: LIMPEZA FINAL DA OBRA | D15: =L15*E15/100 -> #VALUE! | E15: 0 | F15: =$L15*G15/100 -> #VALUE! | G15: 100 | H15: =$L15*I15/100 -> #VALUE! | I15: 100 | J15: =E15+G15 -> 100 | K15: #REF! | L15: =K15*1.4 -> #VALUE! | M15: =L15/$L$21 -> #VALUE!
B16: 10 | C16: RETIRADA DE ENTULHO | D16: =L16*E16/100 -> #VALUE! | E16: 0 | F16: =$L16*G16/100 -> #VALUE! | G16: 0 | H16: =$L16*I16/100 -> #VALUE! | I16: 0 | J16: =E16+G16 -> 0 | K16: #REF! | L16: =K16 -> #REF! | M16: =L16/$L$21 -> #VALUE!
B18: TOTAIS SEMANA (R$) | D18: =SUM(D6:D16) -> #REF! | F18: =SUM(G7:G16) -> 300 | H18: =SUM(I7:I16) -> 300
B19: PORCENTAGEM SEMANA (%) | D19: =D18/$L$21 -> #REF! | F19: =G18/$L$21 -> #REF! | H19: =I18/$L$21 -> #REF!
B20: TOTAIS ACUMULADOS (R$) | D20: =D18 -> #REF! | F20: =G18+E20 -> 0 | H20: =I18+G20 -> 0
B21: PORCENTAGEM ACUMULADAS (%) | D21: =D19 -> #REF! | F21: =G19+E21 -> 0 | H21: =I19+G21 -> 0 | K21: =SUM(K6:K16) -> #REF! | L21: =SUM(L6:L16) -> #REF! | M21: =SUM(M6:M16) -> #REF!
